[{"title": "Guide to reference books.", "author": "Mudge, Isadore Gilbert, 1875-1957.", "id": "iau.31858047547223", "lccA": "Z", "lccN": 1035, "pages": 394, "lang": "eng", "holdings": 158, "cover": "iau.31858047547223"}, {"title": "What to read,", "author": "English, Thomas H. 1895-1992.", "id": "mdp.39015033640288", "lccA": "Z", "lccN": 1035, "pages": 192, "lang": "eng", "holdings": 79, "cover": "mdp.39015033640288"}, {"title": "Readable books in many subjects,", "author": "Felsenthal, Emma.", "id": "mdp.39015033640320", "lccA": "Z", "lccN": 1035, "pages": 36, "lang": "eng", "holdings": 58, "cover": "mdp.39015033640320"}, {"title": "G\u00f6ttinger handkatalog; lesesaalbibliothek, bibliographischer apparat und handmagazin der Universit\u00e4tsbibliothek.", "author": "Universit\u00e4t G\u00f6ttingen. Bibliothek.", "id": "mdp.39015033640346", "lccA": "Z", "lccN": 1035, "pages": 666, "lang": "ger", "holdings": 42, "cover": "mdp.39015033640346"}, {"title": "Katalog der handbibliothek der Orientalischen abteilung.", "author": "Preussische Staatsbibliothek Orientalische abteilung.", "id": "mdp.39015034597370", "lccA": "Z", "lccN": 1035, "pages": 600, "lang": "ger", "holdings": 37, "cover": "mdp.39015034597370"}, {"title": "The booklist /", "author": "", "id": "mdp.39015036942434", "lccA": "Z", "lccN": 1035, "pages": 538, "lang": "eng", "holdings": 3058, "cover": "mdp.39015036942434"}, {"title": "Booklist books.", "author": "American Library Association.", "id": "miun.acw8702.1929.001", "lccA": "Z", "lccN": 1035, "pages": 62, "lang": "eng", "holdings": 74, "cover": "miun.acw8702.1929.001"}, {"title": "The Booklist and subscription books bulletin.", "author": "", "id": "uc1.b2956782", "lccA": "Z", "lccN": 1035, "pages": 562, "lang": "eng", "holdings": 71, "cover": "uc1.b2956782"}, {"title": "Ouvrages remarquables parus dans diffe\u0301rents pays au cours de l'anne\u0301e.", "author": "International Institute of Intellectual Co-operation.", "id": "uc1.b3091216", "lccA": "Z", "lccN": 1035, "pages": 182, "lang": "eng", "holdings": 17, "cover": "uc1.b3091216"}, {"title": "Some reference books of 1928.", "author": "Mudge, Isadore Gilbert, 1875-1957.", "id": "umn.31951p00768835b", "lccA": "Z", "lccN": 1035, "pages": 32, "lang": "eng", "holdings": 1, "cover": "umn.31951p00768835b"}, {"title": "The booklist.", "author": "", "id": "uva.x004352123", "lccA": "Z", "lccN": 1035, "pages": 544, "lang": "eng", "holdings": 455, "cover": "uva.x004352123"}]