[{"title": "Guidance and education of prospective junior wage earners,", "author": "Trumbull, Frederick Marsh.", "id": "mdp.39015027198970", "lccA": "LC", "lccN": 1045, "pages": 366, "lang": "eng", "holdings": 83, "cover": "mdp.39015027198970"}, {"title": "Zhongguo zhi ye jiao yu wen ti /", "author": "Liao, Shicheng, 1892-1970., \u5ed6\u4e16\u627f, 1892-1970.", "id": "mdp.39015027363848", "lccA": "LC", "lccN": 1047, "pages": 282, "lang": "chi", "holdings": 7, "cover": "mdp.39015027363848"}, {"title": "Vocational education,", "author": "Snedden, David, 1868-1951.", "id": "mdp.39015049813374", "lccA": "LC", "lccN": 1045, "pages": 688, "lang": "eng", "holdings": 3, "cover": "mdp.39015049813374"}, {"title": "Efficiency in vocational education.", "author": "Wright, J. C. 1876-", "id": "mdp.39015062732675", "lccA": "LC", "lccN": 1043, "pages": 464, "lang": "eng", "holdings": 82, "cover": "mdp.39015062732675"}, {"title": "A supervised practice program in vocational agriculture /", "author": "Missouri. State board for vocational education.", "id": "mdp.39015065244652", "lccA": "LC", "lccN": 1046, "pages": 104, "lang": "eng", "holdings": 1, "cover": "mdp.39015065244652"}, {"title": "A survey of opportunities for vocational education in Pennsylvania,", "author": "Delaplaine, Meribah.", "id": "mdp.39015067080955", "lccA": "LC", "lccN": 1046, "pages": 216, "lang": "eng", "holdings": 29, "cover": "mdp.39015067080955"}, {"title": "Manual to accompany Vocations in industry;", "author": "Lane, May Rogers, 1878-", "id": "mdp.39015067212079", "lccA": "LC", "lccN": 1045, "pages": 298, "lang": "eng", "holdings": 31, "cover": "mdp.39015067212079"}, {"title": "Bulletin ...", "author": "Oregon. State Board for Vocational Education.", "id": "mdp.39015068145351", "lccA": "LC", "lccN": 1046, "pages": 36, "lang": "eng", "holdings": 3, "cover": "mdp.39015068145351"}, {"title": "Bulletin.", "author": "Wisconsin. State Board of Vocational and Adult Education.", "id": "mdp.39015068527178", "lccA": "LC", "lccN": 1046, "pages": 32, "lang": "eng", "holdings": 4, "cover": "mdp.39015068527178"}, {"title": "The organization and supervision of vocational education in Maryland county high schools,", "author": "Blackwell, Jefferson Davis, 1885-", "id": "mdp.39015069248246", "lccA": "LC", "lccN": 1046, "pages": 206, "lang": "eng", "holdings": 29, "cover": "mdp.39015069248246"}, {"title": "Bulletin.", "author": "United States. Division of Vocational Education.", "id": "mdp.39015069394537", "lccA": "LC", "lccN": 1045, "pages": 1140, "lang": "eng", "holdings": 7, "cover": "mdp.39015069394537"}, {"title": "Trade and industrial education;", "author": "United States. Federal Board for Vocational Education.", "id": "nnc1.cu04277066", "lccA": "LC", "lccN": 1045, "pages": 178, "lang": "eng", "holdings": 28, "cover": "nnc1.cu04277066"}, {"title": "Bulletin /", "author": "", "id": "osu.32435026789065", "lccA": "LC", "lccN": 1045, "pages": 32, "lang": "eng", "holdings": 88, "cover": "osu.32435026789065"}, {"title": "Annual report to Congress of the Federal Board for Vocational Education.", "author": "United States. Federal Board for Vocational Education.", "id": "uc1.b3025073", "lccA": "LC", "lccN": 1045, "pages": 126, "lang": "eng", "holdings": 99, "cover": "uc1.b3025073"}, {"title": "Vocational education.", "author": "Snedden, David, 1868-1951.", "id": "uiug.30112077195177", "lccA": "LC", "lccN": 1043, "pages": 616, "lang": "fre", "holdings": 6, "cover": "uiug.30112077195177"}]