[{"title": "The Airedale,", "author": "Haynes, Williams, 1886-1960.", "id": "iau.31858048125045", "lccA": "SF", "lccN": 429, "pages": 110, "lang": "eng", "holdings": 3, "cover": "iau.31858048125045"}, {"title": "Pure-bred dogs :", "author": "American Kennel Club.", "id": "mdp.39015006891975", "lccA": "SF", "lccN": 427, "pages": 532, "lang": "eng", "holdings": 36, "cover": "mdp.39015006891975"}, {"title": "The Dog fancier.", "author": "", "id": "mdp.39015080367702", "lccA": "SF", "lccN": 421, "pages": 644, "lang": "eng", "holdings": 12, "cover": "mdp.39015080367702"}, {"title": "Recollections of a fox-hunter /", "author": "Horlock, Knightley William, 1802-1882.", "id": "mmet.ark:/13960/t3kw5m75r", "lccA": "SF", "lccN": 429, "pages": 372, "lang": "eng", "holdings": 5, "cover": "mmet.ark:/13960/t3kw5m75r"}, {"title": "A pack of foxhounds /", "author": "Galway, Vere Arundel, Viscount.", "id": "mmet.ark:/13960/t8mc91k8p", "lccA": "SF", "lccN": 429, "pages": 40, "lang": "eng", "holdings": 5, "cover": "mmet.ark:/13960/t8mc91k8p"}, {"title": "American Kennel Club stud book.", "author": "", "id": "osu.32435053119350", "lccA": "SF", "lccN": 423, "pages": 408, "lang": "eng", "holdings": 8, "cover": "osu.32435053119350"}, {"title": "Mongrel, puppy, whelp and hound :", "author": "", "id": "uc1.$b262486", "lccA": "SF", "lccN": 427, "pages": 88, "lang": "eng", "holdings": 16, "cover": "uc1.$b262486"}, {"title": "The popular fox terrier ...", "author": "Skinner, Albert James, 1869-", "id": "uiug.30112020232663", "lccA": "SF", "lccN": 429, "pages": 146, "lang": "eng", "holdings": 9, "cover": "uiug.30112020232663"}, {"title": "Practical dog keeping.", "author": "Haynes, Williams, 1886-1960.", "id": "umn.319510009572320", "lccA": "SF", "lccN": 427, "pages": 168, "lang": "eng", "holdings": 6, "cover": "umn.319510009572320"}, {"title": "Scientific dog feeding :", "author": "Goodrich, Ernest C.", "id": "umn.31951p00274954g", "lccA": "SF", "lccN": 427, "pages": 72, "lang": "eng", "holdings": 4, "cover": "umn.31951p00274954g"}, {"title": "Diet for dogs,", "author": "Little, George Watson.", "id": "wu.89038448767", "lccA": "SF", "lccN": 427, "pages": 288, "lang": "eng", "holdings": 22, "cover": "wu.89038448767"}]