[{"title": "Nevi\u02bcim ah\u0323aronim /", "author": "", "id": "coo.31924076087372", "lccA": "BS", "lccN": 1286, "pages": 394, "lang": "yid", "holdings": 4, "cover": "coo.31924076087372"}, {"title": "Homes of the Psalms;", "author": "Waddy, Percival Stacy, 1875-", "id": "iau.31858048061513", "lccA": "BS", "lccN": 1430, "pages": 304, "lang": "eng", "holdings": 28, "cover": "iau.31858048061513"}, {"title": "The goodly fellowship of the prophets :", "author": "Mackay, W. Mackintosh", "id": "iau.31858048061570", "lccA": "BS", "lccN": 1505, "pages": 280, "lang": "eng", "holdings": 35, "cover": "iau.31858048061570"}, {"title": "The coming prince :", "author": "Anderson, Robert, 1841-1918.", "id": "iau.31858049122389", "lccA": "BS", "lccN": 1556, "pages": 376, "lang": "eng", "holdings": 8, "cover": "iau.31858049122389"}, {"title": "The prophets of Israel /", "author": "Blunt, A. W. F. 1879-1957.", "id": "mdp.39015002859372", "lccA": "BS", "lccN": 1505, "pages": 144, "lang": "eng", "holdings": 73, "cover": "mdp.39015002859372"}, {"title": "The commentry of Rabbi David Himhi on Hosea;", "author": "Kimhi, David, approximately 1160-approximately 1235.", "id": "mdp.39015012324136", "lccA": "BS", "lccN": 1565, "pages": 180, "lang": "eng", "holdings": 26, "cover": "mdp.39015012324136"}, {"title": "The Apocrypha according to the authorized version.", "author": "", "id": "mdp.39015026255326", "lccA": "BS", "lccN": 1692, "pages": 304, "lang": "eng", "holdings": 64, "cover": "mdp.39015026255326"}, {"title": "An interpretation of Genesis,", "author": "Powys, Theodore Francis, 1875-1953.", "id": "mdp.39015026294507", "lccA": "BS", "lccN": 1235, "pages": 134, "lang": "eng", "holdings": 104, "cover": "mdp.39015026294507"}, {"title": "Das Buch Ruth ; Das Buch Judith :", "author": "", "id": "mdp.39015051815507", "lccA": "BS", "lccN": 1314, "pages": 72, "lang": "ger", "holdings": 16, "cover": "mdp.39015051815507"}, {"title": "Mavo sifruti-histori le-khitve ha-kodesh.", "author": "Bernfeld, Simon, 1860-1940.", "id": "mdp.39015055487451", "lccA": "BS", "lccN": 1140, "pages": 422, "lang": "heb", "holdings": 44, "cover": "mdp.39015055487451"}, {"title": "Kommentar zum Alten Testament.", "author": "", "id": "mdp.39015056775219", "lccA": "BS", "lccN": 1154, "pages": 370, "lang": "ger", "holdings": 5, "cover": "mdp.39015056775219"}, {"title": "\u1e24amishah \u1e25umshe Torah :", "author": "", "id": "mdp.39015058506026", "lccA": "BS", "lccN": 1222, "pages": 568, "lang": "heb", "holdings": 1, "cover": "mdp.39015058506026"}, {"title": "Hjemkomst profeten.", "author": "Glahn, Ludvig, 1861-", "id": "mdp.39015068411050", "lccA": "BS", "lccN": 1515, "pages": 304, "lang": "swe", "holdings": 15, "cover": "mdp.39015068411050"}, {"title": "Die fu\u0308nf Bu\u0308cher Moses /", "author": "", "id": "nyp.33433075441521", "lccA": "BS", "lccN": 1224, "pages": 988, "lang": "heb", "holdings": 8, "cover": "nyp.33433075441521"}, {"title": "Meko\u0323r Barukh :", "author": "Fridenberg, Barukh, 1845-1921., \u05e4\u05e8\u05d9\u05d3\u05e0\u05d1\u05e8\u05d2, \u05d1\u05e8\u05d5\u05da, 5481-1291.", "id": "nyp.33433084757842", "lccA": "BS", "lccN": 1158, "pages": 362, "lang": "heb", "holdings": 4, "cover": "nyp.33433084757842"}, {"title": "Teku\u0323fat Yesha\u02bbyahu ve\u0323-he\u0323zyonotav \u0323:", "author": "Vo\u0323hlman, Mendel, 1854-1933.", "id": "nyp.33433104975085", "lccA": "BS", "lccN": 1515, "pages": 342, "lang": "heb", "holdings": 20, "cover": "nyp.33433104975085"}, {"title": "The Book of Job;", "author": "Wray, Newton, 1854-", "id": "osu.32435000402198", "lccA": "BS", "lccN": 1415, "pages": 234, "lang": "eng", "holdings": 29, "cover": "osu.32435000402198"}, {"title": "Segulat Yis\u0301ra\u02bcel :", "author": "Fiv\u0323elzohn, Yis\u0301ra\u02bcel Binyamin Bendet\u0323, 1865-1937., \u05e4\u05d9\u05d1\u05dc\u05d6\u05d5\u05df, \u05d9\u05e9\u05e8\u05d0\u05dc \u05d1\u05e0\u05d9\u05de\u05d9\u05df\u05be\u05d1\u05e0\u05d3\u05d8 \u05d1\u05df \u05d1\u05e8\u05d5\u05da, 1865-1937.", "id": "osu.32435024125346", "lccA": "BS", "lccN": 1235, "pages": 310, "lang": "heb", "holdings": 1, "cover": "osu.32435024125346"}, {"title": "A critical and exegetical commentary on the Books of Samuel /", "author": "Smith, Henry Preserved, 1847-1927.", "id": "osu.32435053601167", "lccA": "BS", "lccN": 1325, "pages": 468, "lang": "eng", "holdings": 30, "cover": "osu.32435053601167"}, {"title": "Mikhah /", "author": "", "id": "osu.32435072006893", "lccA": "BS", "lccN": 1615, "pages": 60, "lang": "heb", "holdings": 1, "cover": "osu.32435072006893"}, {"title": "Torat Ha-Temimah :", "author": "Lipman, Armand,", "id": "osu.32435084217736", "lccA": "BS", "lccN": 1225, "pages": 310, "lang": "fre", "holdings": 2, "cover": "osu.32435084217736"}, {"title": "H\u0323amishah h\u0323umshe Torah.", "author": "", "id": "pst.000001736304", "lccA": "BS", "lccN": 1225, "pages": 580, "lang": "heb", "holdings": 2, "cover": "pst.000001736304"}, {"title": "IV Ezra, a study in the development of universalism,", "author": "Montefiore, C. G. 1858-1938.", "id": "uc1.$b264314", "lccA": "BS", "lccN": 1715, "pages": 92, "lang": "eng", "holdings": 81, "cover": "uc1.$b264314"}, {"title": "A scientific investigation of the Old Testament,", "author": "Wilson, Robert Dick, 1856-1930.", "id": "uc1.$b283799", "lccA": "BS", "lccN": 1171, "pages": 236, "lang": "eng", "holdings": 26, "cover": "uc1.$b283799"}, {"title": "The Psalms;", "author": "", "id": "uc1.$b492473", "lccA": "BS", "lccN": 1424, "pages": 492, "lang": "eng", "holdings": 26, "cover": "uc1.$b492473"}, {"title": "Kohelet,", "author": "Avida, Yehuda Leib, 1887-1962.", "id": "uc1.$b492909", "lccA": "BS", "lccN": 1475, "pages": 154, "lang": "yid", "holdings": 25, "cover": "uc1.$b492909"}, {"title": "El psalteri de Roic\u0327 de Corella :", "author": "", "id": "uc1.31822035057249", "lccA": "BS", "lccN": 1425, "pages": 372, "lang": "cat", "holdings": 2, "cover": "uc1.31822035057249"}, {"title": "Nebuchadnezzar and the story of the fiery furnace :", "author": "", "id": "uc1.31822035057363", "lccA": "BS", "lccN": 1553, "pages": 20, "lang": "eng", "holdings": 28, "cover": "uc1.31822035057363"}, {"title": "1. Mose 14 :", "author": "M\u00fcller, Hans, 1902-", "id": "uc1.b2605323", "lccA": "BS", "lccN": 1235, "pages": 88, "lang": "ger", "holdings": 9, "cover": "uc1.b2605323"}, {"title": "De memoria alterius libri Maccabaeorum.", "author": "Kappler, Werner, 1902-1944.", "id": "uc1.b2620643", "lccA": "BS", "lccN": 1825, "pages": 66, "lang": "lat", "holdings": 11, "cover": "uc1.b2620643"}, {"title": "Das Heiligkeitsgesetz.", "author": "K\u00fcchler, Siegfried, 1900-", "id": "uc1.b2631925", "lccA": "BS", "lccN": 1255, "pages": 66, "lang": "ger", "holdings": 14, "cover": "uc1.b2631925"}, {"title": "Codex Nr. 146,2 Extrav. der Landesbibliothek Wolfenb\u00fcttel :", "author": "Hopfenbeck, Franziska, 1902-", "id": "uc1.b2639090", "lccA": "BS", "lccN": 1430, "pages": 52, "lang": "ger", "holdings": 12, "cover": "uc1.b2639090"}, {"title": "Llyfr y Proffwyd Eseia I-XXXIX :", "author": "", "id": "uc1.b3949567", "lccA": "BS", "lccN": 1515, "pages": 230, "lang": "wel", "holdings": 5, "cover": "uc1.b3949567"}, {"title": "Jeremiah :", "author": "Smith, George Adam, 1856-1942.", "id": "uc1.b4508939", "lccA": "BS", "lccN": 1523, "pages": 432, "lang": "eng", "holdings": 72, "cover": "uc1.b4508939"}, {"title": "The commentary of Rabbi David Kimhi on Hosea;", "author": "Kimhi, David, ca. 1160-ca. 1235.", "id": "uc1.b4588551", "lccA": "BS", "lccN": 1565, "pages": 180, "lang": "heb", "holdings": 58, "cover": "uc1.b4588551"}, {"title": "The book of the twelve prophets,", "author": "Smith, George Adam, Sir, 1856-1942.", "id": "uc1.b5269351", "lccA": "BS", "lccN": 1560, "pages": 474, "lang": "eng", "holdings": 129, "cover": "uc1.b5269351"}, {"title": "The Apocrypha.", "author": "", "id": "uga1.32108036357369", "lccA": "BS", "lccN": 1692, "pages": 366, "lang": "eng", "holdings": 56, "cover": "uga1.32108036357369"}, {"title": "Einleitung in das Alte Testament /", "author": "Sellin, Ernst, 1867-1945.", "id": "uiug.30112113302795", "lccA": "BS", "lccN": 1140, "pages": 208, "lang": "ger", "holdings": 18, "cover": "uiug.30112113302795"}, {"title": "Dodi li-tsevi :", "author": "Rotenstreich, Zebi Tuvyah., \u05e8\u05d5\u05d8\u05d9\u05e0\u05e9\u05d8\u05e8\u05d9\u05da, \u05e6\u05d1\u05d9 \u05d8\u05d5\u05d1\u05d9\u05d4, \u05d4\u05db\u05d4\u05df.", "id": "umd.31430057919708", "lccA": "BS", "lccN": 1430, "pages": 108, "lang": "heb", "holdings": 2, "cover": "umd.31430057919708"}, {"title": "The book of Job: its substance and spirit,", "author": "Jordan, William George, 1854-", "id": "uva.x000938737", "lccA": "BS", "lccN": 1415, "pages": 206, "lang": "eng", "holdings": 122, "cover": "uva.x000938737"}, {"title": "A critical introduction to the Old Testament /", "author": "Gray, George Buchanan, 1865-1922.", "id": "uva.x030120259", "lccA": "BS", "lccN": 1140, "pages": 278, "lang": "eng", "holdings": 17, "cover": "uva.x030120259"}, {"title": "The dramatic story of Old Testament history.", "author": "Price, Ira Maurice, 1856-1939.", "id": "wu.89094587623", "lccA": "BS", "lccN": 1197, "pages": 498, "lang": "eng", "holdings": 101, "cover": "wu.89094587623"}, {"title": "In search of God;", "author": "Powell, John Walker, 1872-1953.", "id": "wu.89094588530", "lccA": "BS", "lccN": 1171, "pages": 168, "lang": "eng", "holdings": 60, "cover": "wu.89094588530"}]