[{"title": "Care of aged persons in the United States ...", "author": "Parker, Florence Evelyn.", "id": "coo.31924002639452", "lccA": "HV", "lccN": 1461, "pages": 328, "lang": "eng", "holdings": 65, "cover": "coo.31924002639452"}, {"title": "Report of the Laura Spelman Rockefeller Memorial.", "author": "Laura Spelman Rockefeller Memorial.", "id": "coo.31924011955287", "lccA": "HV", "lccN": 97, "pages": 186, "lang": "eng", "holdings": 63, "cover": "coo.31924011955287"}, {"title": "Opium, a world problem;", "author": "", "id": "coo.31924012500116", "lccA": "HV", "lccN": 5816, "pages": 408, "lang": "eng", "holdings": 16, "cover": "coo.31924012500116"}, {"title": "Kindheit und Armut;", "author": "Hetzer, Hildegard, 1899-", "id": "coo.31924013789825", "lccA": "HV", "lccN": 713, "pages": 338, "lang": "ger", "holdings": 36, "cover": "coo.31924013789825"}, {"title": "The policeman in Cincinnati ...", "author": "Wykoff, Marguerite.", "id": "coo.31924013850692", "lccA": "HV", "lccN": 8148, "pages": 52, "lang": "eng", "holdings": 9, "cover": "coo.31924013850692"}, {"title": "Die deutsche sozialpolitik im spiegel der statistik.", "author": "Rawicz, Erwin.", "id": "coo.31924013873124", "lccA": "HV", "lccN": 275, "pages": 356, "lang": "ger", "holdings": 26, "cover": "coo.31924013873124"}, {"title": "Laws relating to the Department of social welfare, including Juvenile court law.", "author": "California.", "id": "coo.31924013902717", "lccA": "HV", "lccN": 75, "pages": 72, "lang": "eng", "holdings": 6, "cover": "coo.31924013902717"}, {"title": "Six boys in trouble;", "author": "Reckless, Walter C., 1899-1988.", "id": "coo.31924014006260", "lccA": "HV", "lccN": 9069, "pages": 308, "lang": "eng", "holdings": 40, "cover": "coo.31924014006260"}, {"title": "Het internationale opiumprobleem ...", "author": "Tan, Tong Joe.", "id": "coo.31924023283447", "lccA": "HV", "lccN": 5816, "pages": 202, "lang": "eng", "holdings": 13, "cover": "coo.31924023283447"}, {"title": "China and the problem of narcotics before the League of Nations :", "author": "Wang, Ching-ch\u02bbi, 1882-1941.", "id": "coo.31924023283504", "lccA": "HV", "lccN": 5816, "pages": 34, "lang": "mul", "holdings": 10, "cover": "coo.31924023283504"}, {"title": "Jian yu xue gang yao /", "author": "Xu, Langrong., \u5f90\u6717\u5bb9.", "id": "coo.31924025401278", "lccA": "HV", "lccN": 8669, "pages": 182, "lang": "chi", "holdings": 3, "cover": "coo.31924025401278"}, {"title": "Iz vospominanii\u0306 zhandarma.", "author": "Novit\ufe20s\ufe21kii\u0306, Vasilii\u0306 Dement\u02b9evich.", "id": "coo.31924030328649", "lccA": "HV", "lccN": 8224, "pages": 308, "lang": "rus", "holdings": 6, "cover": "coo.31924030328649"}, {"title": "Journal of juvenile research.", "author": "", "id": "coo.31924066913421", "lccA": "HV", "lccN": 6001, "pages": 322, "lang": "eng", "holdings": 28, "cover": "coo.31924066913421"}, {"title": "Social welfare.", "author": "", "id": "coo.31924070993336", "lccA": "HV", "lccN": 105, "pages": 572, "lang": "eng", "holdings": 27, "cover": "coo.31924070993336"}, {"title": "Mat\u00e9riaux pour l'\u00e9tude des calamit\u00e9s.", "author": "", "id": "coo.31924092234115", "lccA": "HV", "lccN": 553, "pages": 446, "lang": "fre", "holdings": 41, "cover": "coo.31924092234115"}, {"title": "Annual report - Milbank Memorial Fund.", "author": "Milbank Memorial Fund.", "id": "coo.31924092273899", "lccA": "HV", "lccN": 97, "pages": 548, "lang": "eng", "holdings": 119, "cover": "coo.31924092273899"}, {"title": "Annual report.", "author": "Charity Organization Society of Buffalo.", "id": "coo.31924092274087", "lccA": "HV", "lccN": 99, "pages": 356, "lang": "eng", "holdings": 2, "cover": "coo.31924092274087"}, {"title": "Battling the wolves of society;", "author": "Rowell, Earl Albert.", "id": "hvd.32044026193607", "lccA": "HV", "lccN": 5801, "pages": 100, "lang": "eng", "holdings": 18, "cover": "hvd.32044026193607"}, {"title": "The young delinquent.", "author": "Burt, Cyril, 1883-1971", "id": "hvd.32044038182176", "lccA": "HV", "lccN": 9069, "pages": 668, "lang": "eng", "holdings": 17, "cover": "hvd.32044038182176"}, {"title": "Annual report/", "author": "Massachusetts. Department of Public Welfare.", "id": "hvd.32044053448668", "lccA": "HV", "lccN": 86, "pages": 164, "lang": "eng", "holdings": 8, "cover": "hvd.32044053448668"}, {"title": "Obras completas de Concepci\u00f3n Arenal ...", "author": "Arenal de Garc\u00eda Carrasco, Concepci\u00f3n, 1820-1893.", "id": "hvd.32044061965224", "lccA": "HV", "lccN": 15, "pages": 296, "lang": "spa", "holdings": 2, "cover": "hvd.32044061965224"}, {"title": "The Good Will idea /", "author": "Hinckley, G. W. 1853-1950", "id": "hvd.32044088957444", "lccA": "HV", "lccN": 990, "pages": 130, "lang": "eng", "holdings": 9, "cover": "hvd.32044088957444"}, {"title": "Then and now, a friend in need.", "author": "Family Welfare Society of Boston (Boston, Mass.)", "id": "hvd.32044088957501", "lccA": "HV", "lccN": 99, "pages": 40, "lang": "eng", "holdings": 12, "cover": "hvd.32044088957501"}, {"title": "A comparative study of Braille grade one and a half and Braille grade two,", "author": "Irwin, Robert B., 1883-1951", "id": "hvd.32044090910134", "lccA": "HV", "lccN": 1672, "pages": 20, "lang": "eng", "holdings": 4, "cover": "hvd.32044090910134"}, {"title": "Report ...", "author": "Rhode Island. Department of Social Welfare. Division of Probation and Parole.", "id": "hvd.32044097683841", "lccA": "HV", "lccN": 9305, "pages": 22, "lang": "eng", "holdings": 2, "cover": "hvd.32044097683841"}, {"title": "The Mentor ...", "author": "", "id": "hvd.hl1ejc", "lccA": "HV", "lccN": 8301, "pages": 532, "lang": "eng", "holdings": 13, "cover": "hvd.hl1ejc"}, {"title": "Island lantern.", "author": "", "id": "hvd.hl1fic", "lccA": "HV", "lccN": 9474, "pages": 694, "lang": "eng", "holdings": 21, "cover": "hvd.hl1fic"}, {"title": "The Indiana bulletin of charities and correction.", "author": "", "id": "hvd.hl46at", "lccA": "HV", "lccN": 86, "pages": 678, "lang": "eng", "holdings": 26, "cover": "hvd.hl46at"}, {"title": "Prisoners in state and federal prisons and reformatories.", "author": "United States. Bureau of the Census.", "id": "hvd.hl4tgi", "lccA": "HV", "lccN": 7248, "pages": 28, "lang": "eng", "holdings": 2, "cover": "hvd.hl4tgi"}, {"title": "The Comtesse de Saint-G\u00e9ran /", "author": "Dumas, Alexandre, 1802-1870", "id": "hvd.hn618c", "lccA": "HV", "lccN": 6248, "pages": 100, "lang": "eng", "holdings": 22, "cover": "hvd.hn618c"}, {"title": "The case against regulation and control /", "author": "Cherrington, Ernest Hurst, 1877-1950", "id": "hvd.hn67tb", "lccA": "HV", "lccN": 5082, "pages": 8, "lang": "eng", "holdings": 6, "cover": "hvd.hn67tb"}, {"title": "Institutional farms, September 15, 1927, to April 1, 1929 ...", "author": "Pennsylvania. Department of Welfare", "id": "hvd.li1edu", "lccA": "HV", "lccN": 86, "pages": 32, "lang": "eng", "holdings": 4, "cover": "hvd.li1edu"}, {"title": "Child care in institutions /", "author": "Pennsylvania. Department of Welfare. Bureau of Children.", "id": "hvd.li1yds", "lccA": "HV", "lccN": 742, "pages": 36, "lang": "eng", "holdings": 6, "cover": "hvd.li1yds"}, {"title": "The state of the prisons.", "author": "Howard, John, 1726?-1790.", "id": "iau.31858009722087", "lccA": "HV", "lccN": 8980, "pages": 336, "lang": "eng", "holdings": 302, "cover": "iau.31858009722087"}, {"title": "Social case work, generic and specific;", "author": "Milford Conference.", "id": "iau.31858028845869", "lccA": "HV", "lccN": 40, "pages": 110, "lang": "eng", "holdings": 66, "cover": "iau.31858028845869"}, {"title": "Annual report of the Commission for the Blind.", "author": "Iowa Commission for the Blind.", "id": "iau.31858041913660", "lccA": "HV", "lccN": 1796, "pages": 20, "lang": "eng", "holdings": 13, "cover": "iau.31858041913660"}, {"title": "The Howard journal :", "author": "", "id": "iau.31858045155193", "lccA": "HV", "lccN": 8995, "pages": 412, "lang": "eng", "holdings": 80, "cover": "iau.31858045155193"}, {"title": "Bulletin of state institutions.", "author": "", "id": "iau.31858045516469", "lccA": "HV", "lccN": 86, "pages": 292, "lang": "eng", "holdings": 31, "cover": "iau.31858045516469"}, {"title": "Hospital social service.", "author": "", "id": "iau.31858046172767", "lccA": "HV", "lccN": 687, "pages": 576, "lang": "eng", "holdings": 49, "cover": "iau.31858046172767"}, {"title": "The Mu\u0308ller-Walle method of lip-reading for the deaf (Bruhn lip-reading system) /", "author": "Bruhn, Martha Emma, 1872-", "id": "iau.31858046366997", "lccA": "HV", "lccN": 2487, "pages": 304, "lang": "eng", "holdings": 26, "cover": "iau.31858046366997"}, {"title": "The inside of prohibition,", "author": "Willebrandt, Mabel Walker, 1889-1963.", "id": "ien.35556001346477", "lccA": "HV", "lccN": 5089, "pages": 353, "lang": "eng", "holdings": 152, "cover": "ien.35556001346477"}, {"title": "Boys' workers round table.", "author": "", "id": "inu.30000047595339", "lccA": "HV", "lccN": 701, "pages": 460, "lang": "eng", "holdings": 11, "cover": "inu.30000047595339"}, {"title": "Annual report /", "author": "Rockefeller Foundation.", "id": "inu.30000054451327", "lccA": "HV", "lccN": 97, "pages": 428, "lang": "eng", "holdings": 364, "cover": "inu.30000054451327"}, {"title": "The guillotine and its servants,", "author": "Lenotre, G., 1855-1935.", "id": "inu.32000003468941", "lccA": "HV", "lccN": 8555, "pages": 296, "lang": "eng", "holdings": 88, "cover": "inu.32000003468941"}, {"title": "Proceedings of the ... Minnesota State Conference of Charities and Correction.", "author": "Minnesota State Conference of Charities and Correction.", "id": "inu.32000007309307", "lccA": "HV", "lccN": 88, "pages": 180, "lang": "eng", "holdings": 8, "cover": "inu.32000007309307"}, {"title": "The sterilization of the unfit /", "author": "Gallichan, Walter M. 1861-1946.", "id": "inu.32000007472717", "lccA": "HV", "lccN": 4989, "pages": 204, "lang": "eng", "holdings": 42, "cover": "inu.32000007472717"}, {"title": "Scritti in onore di Enrico Ferri per il cinquantesimo anno di suo insegnamento universitario;", "author": "", "id": "mdp.35112104694437", "lccA": "HV", "lccN": 6016, "pages": 542, "lang": "ita", "holdings": 14, "cover": "mdp.35112104694437"}, {"title": "\"La criminalidad pol\u00edtica\";", "author": "Martinez, Jos\u00e9 Agustin.", "id": "mdp.35112104719721", "lccA": "HV", "lccN": 6301, "pages": 282, "lang": "spa", "holdings": 4, "cover": "mdp.35112104719721"}, {"title": "The report of the American Red cross commission to China.", "author": "Red cross. U.S. American national Red cross. Commission to China.", "id": "mdp.39015002687112", "lccA": "HV", "lccN": 575, "pages": 112, "lang": "eng", "holdings": 84, "cover": "mdp.39015002687112"}, {"title": "The state of the poor;", "author": "Eden, Frederick Morton, Sir, 1766-1809,", "id": "mdp.39015004832724", "lccA": "HV", "lccN": 245, "pages": 448, "lang": "eng", "holdings": 80, "cover": "mdp.39015004832724"}, {"title": "The West Indies hurricane disaster, September, 1928;", "author": "American National Red Cross.", "id": "mdp.39015005004760", "lccA": "HV", "lccN": 575, "pages": 104, "lang": "eng", "holdings": 42, "cover": "mdp.39015005004760"}, {"title": "On capital punishment,", "author": "Wells, Gabriel, 1862-1946.", "id": "mdp.39015005392033", "lccA": "HV", "lccN": 8698, "pages": 28, "lang": "eng", "holdings": 38, "cover": "mdp.39015005392033"}, {"title": "Scotland yard and the metropolitan police.", "author": "Moylan, John Fitzgerald, Sir, 1882-", "id": "mdp.39015005615318", "lccA": "HV", "lccN": 8198, "pages": 370, "lang": "eng", "holdings": 117, "cover": "mdp.39015005615318"}, {"title": "Reconstructing behavior in youth;", "author": "Healy, William, 1869-1963.", "id": "mdp.39015005756187", "lccA": "HV", "lccN": 875, "pages": 362, "lang": "eng", "holdings": 322, "cover": "mdp.39015005756187"}, {"title": "The Commonwealth fund activities in Austria 1923-1929", "author": "Commonwealth Fund. Division for Austria.", "id": "mdp.39015007324562", "lccA": "HV", "lccN": 759, "pages": 176, "lang": "eng", "holdings": 85, "cover": "mdp.39015007324562"}, {"title": "The Near East and American philanthropy :", "author": "General Committee of the Near East Survey.", "id": "mdp.39015008008784", "lccA": "HV", "lccN": 380, "pages": 330, "lang": "eng", "holdings": 196, "cover": "mdp.39015008008784"}, {"title": "It's a racket! /", "author": "Hostetter, Gordon L.", "id": "mdp.39015008619184", "lccA": "HV", "lccN": 6795, "pages": 346, "lang": "eng", "holdings": 134, "cover": "mdp.39015008619184"}, {"title": "Mes souvenirs.", "author": "L\u00e9pine, Louis, 1846-1933.", "id": "mdp.39015009223978", "lccA": "HV", "lccN": 7915, "pages": 324, "lang": "fre", "holdings": 38, "cover": "mdp.39015009223978"}, {"title": "Training schools for delinquent girls,", "author": "Reeves, Margaret.", "id": "mdp.39015009326904", "lccA": "HV", "lccN": 9104, "pages": 496, "lang": "eng", "holdings": 196, "cover": "mdp.39015009326904"}, {"title": "Prohibition quiz book ;", "author": "Doty, Boyd P.,", "id": "mdp.39015010470980", "lccA": "HV", "lccN": 5089, "pages": 138, "lang": "eng", "holdings": 56, "cover": "mdp.39015010470980"}, {"title": "The Survey.", "author": "", "id": "mdp.39015010567777", "lccA": "HV", "lccN": 1, "pages": 684, "lang": "eng", "holdings": 124, "cover": "mdp.39015010567777"}, {"title": "Annual report of the Children's Court of the City of New York.", "author": "New York (State). Children's Court (New York)", "id": "mdp.39015010803800", "lccA": "HV", "lccN": 9094, "pages": 60, "lang": "eng", "holdings": 19, "cover": "mdp.39015010803800"}, {"title": "Bezprizornye /", "author": "Zenzinov, V. 1880-1953., \u0417\u0435\u043d\u0437\u0438\u043d\u043e\u0432, \u0412. 1880-1953.", "id": "mdp.39015011954057", "lccA": "HV", "lccN": 782, "pages": 336, "lang": "rus", "holdings": 49, "cover": "mdp.39015011954057"}, {"title": "Rattling the cup on Chicago crime", "author": "Sullivan, Edward Dean, 1888-1938.", "id": "mdp.39015014153905", "lccA": "HV", "lccN": 6795, "pages": 244, "lang": "eng", "holdings": 124, "cover": "mdp.39015014153905"}, {"title": "Child welfare.", "author": "League of Nations. Assembly. Fifth Committee.", "id": "mdp.39015014700630", "lccA": "HV", "lccN": 703, "pages": 14, "lang": "eng", "holdings": 15, "cover": "mdp.39015014700630"}, {"title": "Traffic in opium and other dangerous drugs.", "author": "League of Nations. Assembly. Fifth Committee.", "id": "mdp.39015016465265", "lccA": "HV", "lccN": 5816, "pages": 12, "lang": "eng", "holdings": 7, "cover": "mdp.39015016465265"}, {"title": "The great pearl robbery of 1913; :", "author": "Humphreys, Christmas, 1901-1983.", "id": "mdp.39015020699701", "lccA": "HV", "lccN": 6665, "pages": 352, "lang": "eng", "holdings": 51, "cover": "mdp.39015020699701"}, {"title": "Hull-house year book.", "author": "Hull-House (Chicago, Ill.)", "id": "mdp.39015020721083", "lccA": "HV", "lccN": 4196, "pages": 72, "lang": "eng", "holdings": 69, "cover": "mdp.39015020721083"}, {"title": "Archiv fu\u0308r Kriminologie.", "author": "", "id": "mdp.39015021267607", "lccA": "HV", "lccN": 6003, "pages": 588, "lang": "ger", "holdings": 12, "cover": "mdp.39015021267607"}, {"title": "You can escape,", "author": "Smith, Edward H. 1881-1927.", "id": "mdp.39015022203932", "lccA": "HV", "lccN": 8657, "pages": 394, "lang": "eng", "holdings": 58, "cover": "mdp.39015022203932"}, {"title": "The Anti-saloon league year book;", "author": "", "id": "mdp.39015024030853", "lccA": "HV", "lccN": 5286, "pages": 226, "lang": "eng", "holdings": 270, "cover": "mdp.39015024030853"}, {"title": "Report.", "author": "Rhode Island. State Public Welfare Commission.", "id": "mdp.39015024048855", "lccA": "HV", "lccN": 86, "pages": 120, "lang": "eng", "holdings": 10, "cover": "mdp.39015024048855"}, {"title": "Federal penal and reformatory institutions.", "author": "United States. Congress. House. Special committee on federal penal and reformatory institutions.", "id": "mdp.39015024880828", "lccA": "HV", "lccN": 8314, "pages": 316, "lang": "eng", "holdings": 18, "cover": "mdp.39015024880828"}, {"title": "The social worker in family, medical and psychiatric social work,", "author": "Odencrantz, Louise C. 1884-1969.", "id": "mdp.39015027568354", "lccA": "HV", "lccN": 40, "pages": 406, "lang": "eng", "holdings": 181, "cover": "mdp.39015027568354"}, {"title": "The trial of Herbert John Bennett", "author": "Bennett, Herbert John, 1880-1901,", "id": "mdp.39015027579435", "lccA": "HV", "lccN": 6542, "pages": 234, "lang": "eng", "holdings": 65, "cover": "mdp.39015027579435"}, {"title": "The invisible web;", "author": "Ashton-Wolfe, H. 1881-", "id": "mdp.39015027609901", "lccA": "HV", "lccN": 6970, "pages": 342, "lang": "eng", "holdings": 23, "cover": "mdp.39015027609901"}, {"title": "Law observance.", "author": "Durant, William Crapo, 1861-1947.", "id": "mdp.39015027610032", "lccA": "HV", "lccN": 5089, "pages": 590, "lang": "eng", "holdings": 409, "cover": "mdp.39015027610032"}, {"title": "Bandits and the Southern Pacific,", "author": "Glasscock, Carl B. 1884-1942.", "id": "mdp.39015028062233", "lccA": "HV", "lccN": 6793, "pages": 324, "lang": "eng", "holdings": 133, "cover": "mdp.39015028062233"}, {"title": "The behavior-problem boy,", "author": "Owens, Albert A. 1896-1956.", "id": "mdp.39015028071150", "lccA": "HV", "lccN": 9069, "pages": 200, "lang": "eng", "holdings": 61, "cover": "mdp.39015028071150"}, {"title": "Canadian penal institutions,", "author": "Topping, C. W. 1889-", "id": "mdp.39015028072547", "lccA": "HV", "lccN": 9504, "pages": 166, "lang": "eng", "holdings": 35, "cover": "mdp.39015028072547"}, {"title": "Safety education in the secondary schools: objectives and materials of instruction.", "author": "Stack, Herbert James, 1892-1967.", "id": "mdp.39015028108960", "lccA": "HV", "lccN": 676, "pages": 172, "lang": "eng", "holdings": 19, "cover": "mdp.39015028108960"}, {"title": "Three laws affecting Kansas children.", "author": "Kansas.", "id": "mdp.39015028109331", "lccA": "HV", "lccN": 725, "pages": 20, "lang": "eng", "holdings": 1, "cover": "mdp.39015028109331"}, {"title": "Twenty-five years of the Carnegie hero fund, 1904-1929.", "author": "Holland, W. J. 1848-1932.", "id": "mdp.39015028144049", "lccA": "HV", "lccN": 670, "pages": 28, "lang": "eng", "holdings": 7, "cover": "mdp.39015028144049"}, {"title": "V sovi\u0361etskom sudi\u0361e :", "author": "Braude, Il\u02b9i\u0361a Davidovich.", "id": "mdp.39015028303728", "lccA": "HV", "lccN": 7012, "pages": 182, "lang": "rus", "holdings": 24, "cover": "mdp.39015028303728"}, {"title": "Verbrechen als Schicksal;", "author": "Lange, Johannes, 1891-1938.", "id": "mdp.39015030567757", "lccA": "HV", "lccN": 6121, "pages": 100, "lang": "ger", "holdings": 73, "cover": "mdp.39015030567757"}, {"title": "Mental hygiene and social work,", "author": "Lee, Porter R. 1879-1946.", "id": "mdp.39015030568086", "lccA": "HV", "lccN": 11, "pages": 340, "lang": "eng", "holdings": 190, "cover": "mdp.39015030568086"}, {"title": "Sc\u00e8nes du monde criminel russe;", "author": "Koshko, A. F. 1867-1928 or 1929.", "id": "mdp.39015030677135", "lccA": "HV", "lccN": 7012, "pages": 396, "lang": "fre", "holdings": 17, "cover": "mdp.39015030677135"}, {"title": "Boys and girls in Salt Lake City;", "author": "Beeley, Arthur L. 1890-1973.", "id": "mdp.39015030793619", "lccA": "HV", "lccN": 743, "pages": 234, "lang": "eng", "holdings": 40, "cover": "mdp.39015030793619"}, {"title": "Four year report (1923 to 1926 inclusive) of the Central clinic of the Community chest and Council of social agencies, Cincinnati, Ohio.", "author": "Cincinnati (Ohio). Central clinic.", "id": "mdp.39015031220612", "lccA": "HV", "lccN": 3006, "pages": 84, "lang": "eng", "holdings": 7, "cover": "mdp.39015031220612"}, {"title": "Crime in ink.", "author": "Carvalho, Claire.", "id": "mdp.39015031447827", "lccA": "HV", "lccN": 8074, "pages": 320, "lang": "eng", "holdings": 76, "cover": "mdp.39015031447827"}, {"title": "Indian village crimes,", "author": "Walsh, Cecil Henry, Sir, 1869-1946.", "id": "mdp.39015031449765", "lccA": "HV", "lccN": 7092, "pages": 260, "lang": "eng", "holdings": 79, "cover": "mdp.39015063050499"}, {"title": "Report of statistician.", "author": "Illinois. Department of Public Welfare.", "id": "mdp.39015031664850", "lccA": "HV", "lccN": 86, "pages": 282, "lang": "eng", "holdings": 13, "cover": "mdp.39015031664850"}, {"title": "Handbook of American prisons and reformatories.", "author": "", "id": "mdp.39015031985412", "lccA": "HV", "lccN": 9471, "pages": 1108, "lang": "eng", "holdings": 86, "cover": "mdp.39015031985412"}, {"title": "Turning over a new leaf :", "author": "", "id": "mdp.39015032541289", "lccA": "HV", "lccN": 9303, "pages": 36, "lang": "eng", "holdings": 2, "cover": "mdp.39015032541289"}, {"title": "Indiana conference on law observance and enforcement,", "author": "Indiana conference on law observance and enforcement, Indianapolis, (1929)", "id": "mdp.39015033208730", "lccA": "HV", "lccN": 6793, "pages": 152, "lang": "eng", "holdings": 26, "cover": "mdp.39015033208730"}, {"title": "The prisoner's antecedents.", "author": "United States. Bureau of the Census.", "id": "mdp.39015033515605", "lccA": "HV", "lccN": 7248, "pages": 90, "lang": "eng", "holdings": 13, "cover": "mdp.39015033515605"}, {"title": "Stealing through life", "author": "Booth, Ernest, 1899-", "id": "mdp.39015033858773", "lccA": "HV", "lccN": 6248, "pages": 322, "lang": "eng", "holdings": 84, "cover": "mdp.39015033858773"}, {"title": "The Mississippi valley flood disaster of 1927;", "author": "American National Red Cross.", "id": "mdp.39015033926133", "lccA": "HV", "lccN": 575, "pages": 192, "lang": "eng", "holdings": 132, "cover": "mdp.39015033926133"}, {"title": "T\u014dky\u014d-fu Shakai Jigy\u014d Ky\u014dkai h\u014d.", "author": "", "id": "mdp.39015034163843", "lccA": "HV", "lccN": 411, "pages": 604, "lang": "jpn", "holdings": 2, "cover": "mdp.39015034163843"}, {"title": "Scandals of prohibition enforcement.", "author": "Association Against the Prohibition Amendment.", "id": "mdp.39015035011132", "lccA": "HV", "lccN": 5089, "pages": 40, "lang": "eng", "holdings": 25, "cover": "mdp.39015035011132"}, {"title": "Reforming America with a shotgun;", "author": "Association Against the Prohibition Amendment.", "id": "mdp.39015035011272", "lccA": "HV", "lccN": 5089, "pages": 48, "lang": "eng", "holdings": 16, "cover": "mdp.39015035011272"}, {"title": "The enforcement of the Eighteenth amendment and the Volstead act from the point of view of the individual states,", "author": "Ritchie, Albert C. 1876-1936.", "id": "mdp.39015035016131", "lccA": "HV", "lccN": 5089, "pages": 20, "lang": "eng", "holdings": 11, "cover": "mdp.39015035016131"}, {"title": "Annual report of statistics of criminal and other offences.", "author": "Statistics Canada. Judicial Division.", "id": "mdp.39015035426140", "lccA": "HV", "lccN": 7315, "pages": 1404, "lang": "eng", "holdings": 61, "cover": "mdp.39015035426140"}, {"title": "Police administration in New York, Chicago and Philadelphia,", "author": "Chang, Ching Hui, 1900-", "id": "mdp.39015035453847", "lccA": "HV", "lccN": 8138, "pages": 28, "lang": "eng", "holdings": 16, "cover": "mdp.39015035453847"}, {"title": "Laws relating to the Department of social welfare, including the Juvenile court law.", "author": "California.", "id": "mdp.39015036635400", "lccA": "HV", "lccN": 74, "pages": 66, "lang": false, "holdings": null, "cover": "mdp.39015036635400"}, {"title": "Report.", "author": "Buhl Foundation.", "id": "mdp.39015039315240", "lccA": "HV", "lccN": 99, "pages": 46, "lang": "eng", "holdings": 31, "cover": "mdp.39015039315240"}, {"title": "The social welfare forum. :", "author": "National Conference on Social Welfare. Forum.", "id": "mdp.39015039339372", "lccA": "HV", "lccN": 88, "pages": 706, "lang": "eng", "holdings": 363, "cover": "mdp.39015039339372"}, {"title": "Report.", "author": "Illinois. Department of Public Welfare.", "id": "mdp.39015039397354", "lccA": "HV", "lccN": 86, "pages": 558, "lang": "eng", "holdings": 2, "cover": "mdp.39015039397354"}, {"title": "Social work year book.", "author": "", "id": "mdp.39015039398543", "lccA": "HV", "lccN": 35, "pages": 616, "lang": "eng", "holdings": 6, "cover": "mdp.39015039398543"}, {"title": "Special bulletin.", "author": "", "id": "mdp.39015039399335", "lccA": "HV", "lccN": 98, "pages": 180, "lang": "eng", "holdings": 15, "cover": "mdp.39015039399335"}, {"title": "Annual report of the Department of Public Welfare.", "author": "Ohio. Department of Public Welfare.", "id": "mdp.39015039399590", "lccA": "HV", "lccN": 86, "pages": 680, "lang": "eng", "holdings": 44, "cover": "mdp.39015039399590"}, {"title": "Biennial report.", "author": "North Carolina. Department of Social Services.", "id": "mdp.39015039710440", "lccA": "HV", "lccN": 86, "pages": 106, "lang": "eng", "holdings": 13, "cover": "mdp.39015039710440"}, {"title": "The Police journal.", "author": "", "id": "mdp.39015039711281", "lccA": "HV", "lccN": 7551, "pages": 770, "lang": "eng", "holdings": 166, "cover": "mdp.39015039711281"}, {"title": "The New outlook for the blind.", "author": "", "id": "mdp.39015039711828", "lccA": "HV", "lccN": 1571, "pages": 568, "lang": "eng", "holdings": 225, "cover": "mdp.39015039711828"}, {"title": "Oralism and auralism.", "author": "", "id": "mdp.39015039712156", "lccA": "HV", "lccN": 2510, "pages": 496, "lang": "eng", "holdings": 12, "cover": "mdp.39015039712156"}, {"title": "Yearbook.", "author": "National Council on Crime and Delinquency.", "id": "mdp.39015039713469", "lccA": "HV", "lccN": 9303, "pages": 280, "lang": "eng", "holdings": 66, "cover": "mdp.39015039713469"}, {"title": "Report of the Royal Canadian Mounted Police.", "author": "Royal Canadian Mounted Police.", "id": "mdp.39015039713816", "lccA": "HV", "lccN": 7641, "pages": 148, "lang": "eng", "holdings": 43, "cover": "mdp.39015039713816"}, {"title": "Report ...", "author": "New York (State). Division of Probation.", "id": "mdp.39015039717999", "lccA": "HV", "lccN": 9305, "pages": 234, "lang": "eng", "holdings": 27, "cover": "mdp.39015039717999"}, {"title": "American annals of the deaf.", "author": "", "id": "mdp.39015039725489", "lccA": "HV", "lccN": 2510, "pages": 548, "lang": "eng", "holdings": 592, "cover": "mdp.39015039725489"}, {"title": "Canada liquor crossing the border /", "author": "Association Against the Prohibition Amendment.", "id": "mdp.39015041742365", "lccA": "HV", "lccN": 5089, "pages": 34, "lang": "eng", "holdings": 17, "cover": "mdp.39015041742365"}, {"title": "Keisatsu to\u0304kei ho\u0304koku.", "author": "", "id": "mdp.39015041940142", "lccA": "HV", "lccN": 8257, "pages": 188, "lang": "jpn", "holdings": 6, "cover": "mdp.39015041940142"}, {"title": "The trial of Count K\u00f6nigsmarck,", "author": "K\u00f6nigsmarck, Karl Johan von, grefve, 1659-1686,", "id": "mdp.39015050563462", "lccA": "HV", "lccN": 6248, "pages": 220, "lang": "eng", "holdings": 40, "cover": "mdp.39015050563462"}, {"title": "Laws relating to national prohibition enforcement.", "author": "United States.", "id": "mdp.39015050565947", "lccA": "HV", "lccN": 5076, "pages": 148, "lang": "eng", "holdings": 2, "cover": "mdp.39015050565947"}, {"title": "The morality of punishment :", "author": "Ewing, A. C. 1899-1973.", "id": "mdp.39015053139708", "lccA": "HV", "lccN": 8675, "pages": 256, "lang": "eng", "holdings": 127, "cover": "mdp.39015053139708"}, {"title": "Fun yor tsu yor.", "author": "", "id": "mdp.39015059735418", "lccA": "HV", "lccN": 1215, "pages": 234, "lang": "yid", "holdings": 15, "cover": "mdp.39015059735418"}, {"title": "The Volta review", "author": "", "id": "mdp.39015060425199", "lccA": "HV", "lccN": 2350, "pages": 894, "lang": "eng", "holdings": 556, "cover": "mdp.39015060425199"}, {"title": "Day schools vs. institutions for the deaf;", "author": "Upshall, Charles Cecil, 1901-", "id": "mdp.39015063049335", "lccA": "HV", "lccN": 2530, "pages": 120, "lang": "eng", "holdings": 6, "cover": "mdp.39015063049335"}, {"title": "An International year book of child care and protection;", "author": "", "id": "mdp.39015063081411", "lccA": "HV", "lccN": 701, "pages": 680, "lang": "eng", "holdings": 62, "cover": "mdp.39015063081411"}, {"title": "Vocational research series.", "author": "American Foundation for the Blind.", "id": "mdp.39015063081536", "lccA": "HV", "lccN": 1571, "pages": 56, "lang": "eng", "holdings": 2, "cover": "mdp.39015063081536"}, {"title": "Annual report.", "author": "Indiana. School for the Deaf, Indianapolis.", "id": "mdp.39015063083110", "lccA": "HV", "lccN": 2561, "pages": 84, "lang": "eng", "holdings": 5, "cover": "mdp.39015063083110"}, {"title": "A study of problem boys and their brothers by the sub commission on causes and effects of crime. 1828.", "author": "New York (State). Crime Commission.", "id": "mdp.39015063689148", "lccA": "HV", "lccN": 9051, "pages": 422, "lang": "eng", "holdings": 1, "cover": "mdp.39015063689148"}, {"title": "Oliver untwisted.", "author": "Payne, Muriel Amy.", "id": "mdp.39015063734381", "lccA": "HV", "lccN": 965, "pages": 136, "lang": "eng", "holdings": 50, "cover": "mdp.39015063734381"}, {"title": "Documents relatifs \u00e0 la r\u00e9glementation de l'assistance publique \u00e0 Mons du XVe au XVIIIe si\u00e8cle.", "author": "Heupgen, Paul,", "id": "mdp.39015063921442", "lccA": "HV", "lccN": 305, "pages": 336, "lang": "fre", "holdings": 34, "cover": "mdp.39015063921442"}, {"title": "Ten years in a London slum :", "author": "Morse-Boycott, Desmond Lionel, 1892-", "id": "mdp.39015064794038", "lccA": "HV", "lccN": 4088, "pages": 330, "lang": "eng", "holdings": 20, "cover": "mdp.39015064794038"}, {"title": "Neighborhood;", "author": "", "id": "mdp.39015067285778", "lccA": "HV", "lccN": 4175, "pages": 676, "lang": "eng", "holdings": 28, "cover": "mdp.39015067285778"}, {"title": "Traffic in opium and other dangerous drugs ...", "author": "United States. Federal narcotics board.", "id": "mdp.39015068263394", "lccA": "HV", "lccN": 5825, "pages": 38, "lang": "eng", "holdings": 3, "cover": "mdp.39015068263394"}, {"title": "Bolet\u00edn de la asistencia p\u00fablica nacional.", "author": "Uruguay. Direcci\u00f3n General de la Asistencia P\u00fablica.", "id": "mdp.39015069771494", "lccA": "HV", "lccN": 226, "pages": 294, "lang": "spa", "holdings": 5, "cover": "mdp.39015069771494"}, {"title": "Robert A. Woods, champion of democracy,", "author": "Woods, Eleanor H.", "id": "mdp.39015070585495", "lccA": "HV", "lccN": 28, "pages": 408, "lang": "eng", "holdings": 115, "cover": "mdp.39015070585495"}, {"title": "Shakai jigy\u014d no tomo.", "author": "", "id": "mdp.39015070817682", "lccA": "HV", "lccN": 428, "pages": 402, "lang": "jpn", "holdings": 9, "cover": "mdp.39015070817682"}, {"title": "Report of the Department of Public Safety of the State of Michigan.", "author": "Michigan. Department of Public Safety.", "id": "mdp.39015071125788", "lccA": "HV", "lccN": 7571, "pages": 56, "lang": "eng", "holdings": 13, "cover": "mdp.39015071125788"}, {"title": "Annual convention of the State Association of Superintendents of the Poor, City Directors of Public Welfare and the Keepers and Matrons of County Infirmaries.", "author": "State Association of Superintendents of the Poor, City Directors of Public Welfare and the Keepers and Matrons of County Infirmaries (Mich.). Convention.", "id": "mdp.39015071269925", "lccA": "HV", "lccN": 88, "pages": 100, "lang": "eng", "holdings": 3, "cover": "mdp.39015071269925"}, {"title": "Raittiuskansan Kalenteri.", "author": "", "id": "mdp.39015071389624", "lccA": "HV", "lccN": 5286, "pages": 236, "lang": "fin", "holdings": 6, "cover": "mdp.39015071389624"}, {"title": "The last outposts of prohibition in Canada: Nova Scotia and Prince Edward Island.", "author": "Association Against the Prohibition Amendment.", "id": "mdp.39015071420080", "lccA": "HV", "lccN": 5072, "pages": 44, "lang": "eng", "holdings": 23, "cover": "mdp.39015071420080"}, {"title": "Quiz book :", "author": "Doty, Boyd P.", "id": "mdp.39015071421823", "lccA": "HV", "lccN": 5089, "pages": 66, "lang": "eng", "holdings": 24, "cover": "mdp.39015071421823"}, {"title": "Fundamental facts for patriots :", "author": "", "id": "mdp.39015071422367", "lccA": "HV", "lccN": 5089, "pages": 36, "lang": "eng", "holdings": 19, "cover": "mdp.39015071422367"}, {"title": "What is prohibition? :", "author": "Godwin, Earl, 1881-1956.", "id": "mdp.39015071422474", "lccA": "HV", "lccN": 5089, "pages": 48, "lang": "eng", "holdings": 20, "cover": "mdp.39015071422474"}, {"title": "Prohibition, nullification and lawlessness :", "author": "McAdoo, W. G. 1863-1941.", "id": "mdp.39015071646587", "lccA": "HV", "lccN": 5089, "pages": 40, "lang": "eng", "holdings": 13, "cover": "mdp.39015071646587"}, {"title": "The world's new day and alcohol /", "author": "Stoddard, Cora F. 1872-1936.", "id": "mdp.39015071648955", "lccA": "HV", "lccN": 5060, "pages": 82, "lang": "eng", "holdings": 21, "cover": "mdp.39015071648955"}, {"title": "\"They almost had me fooled\" :", "author": "", "id": "mdp.39015071649144", "lccA": "HV", "lccN": 5090, "pages": 100, "lang": "eng", "holdings": 11, "cover": "mdp.39015071649144"}, {"title": "Proceedings of the meeting of the Convention of American Instructors of the Deaf.", "author": "Convention of American Instructors of the Deaf.", "id": "mdp.39015073401393", "lccA": "HV", "lccN": 2522, "pages": 196, "lang": "eng", "holdings": 10, "cover": "mdp.39015073401393"}, {"title": "Biennial report.", "author": "Oregon. Supreme Court. Library.", "id": "mdp.39015073698642", "lccA": "HV", "lccN": 86, "pages": 216, "lang": "eng", "holdings": 43, "cover": "mdp.39015073698642"}, {"title": "La revue philanthropique.", "author": "", "id": "mdp.39015073808597", "lccA": "HV", "lccN": 2, "pages": 1070, "lang": "fre", "holdings": 26, "cover": "mdp.39015073808597"}, {"title": "Le Service social.", "author": "", "id": "mdp.39015073808738", "lccA": "HV", "lccN": 1, "pages": 40, "lang": "fre", "holdings": 12, "cover": "mdp.39015073808738"}, {"title": "Day schools vs. institutions for the deaf:", "author": "Upshall, Charles Cecil, 1901-", "id": "mdp.39015074137681", "lccA": "HV", "lccN": 2530, "pages": 120, "lang": "eng", "holdings": 102, "cover": "mdp.39015074137681"}, {"title": "Annual report of the Columbia Institution for the Deaf to the Secretary of the Interior.", "author": "Columbia Institution for the Deaf (Washington, D.C.)", "id": "mdp.39015074670491", "lccA": "HV", "lccN": 2561, "pages": 16, "lang": "eng", "holdings": 31, "cover": "mdp.39015074670491"}, {"title": "Annual report.", "author": "New York. Institution for Improved Instruction of Deaf Mutes, New York.", "id": "mdp.39015074671002", "lccA": "HV", "lccN": 2561, "pages": 32, "lang": "eng", "holdings": 2, "cover": "mdp.39015074671002"}, {"title": "Fifteen years of the drink question in Massachusetts,", "author": "Stoddard, Cora F. 1872-1936.", "id": "mdp.39015074684385", "lccA": "HV", "lccN": 5090, "pages": 128, "lang": "eng", "holdings": 63, "cover": "mdp.39015074684385"}, {"title": "Annual report.", "author": "China. National Opium Suppression Committee", "id": "mdp.39015074685127", "lccA": "HV", "lccN": 5816, "pages": 112, "lang": "eng", "holdings": 1, "cover": "mdp.39015074685127"}, {"title": "A guide for preparing annual police reports.", "author": "International Association of Chiefs of Police. Committee on Uniform Crime Records.", "id": "mdp.39015074687875", "lccA": "HV", "lccN": 6018, "pages": 44, "lang": "eng", "holdings": 1, "cover": "mdp.39015074687875"}, {"title": "Report [of the] Department of Correction.", "author": "Maryland. Board of Correction.", "id": "mdp.39015074689186", "lccA": "HV", "lccN": 8340, "pages": 108, "lang": "eng", "holdings": 4, "cover": "mdp.39015074689186"}, {"title": "Annual report.", "author": "Massachusetts. Department of Public Welfare.", "id": "mdp.39015074689616", "lccA": "HV", "lccN": 86, "pages": 164, "lang": "eng", "holdings": 8, "cover": "mdp.39015074689616"}, {"title": "Report.", "author": "Indiana. Girls' School, Indianapolis.", "id": "mdp.39015074691745", "lccA": "HV", "lccN": 9105, "pages": 36, "lang": "eng", "holdings": 4, "cover": "mdp.39015074691745"}, {"title": "Juvenile courts in Utah;", "author": "National Council on Crime and Delinquency.", "id": "mdp.39015074692248", "lccA": "HV", "lccN": 9093, "pages": 88, "lang": "eng", "holdings": 27, "cover": "mdp.39015074692248"}, {"title": "Annual report of the New York State Commission of Correction.", "author": "New York (State). State Commission of Correction.", "id": "mdp.39015074694764", "lccA": "HV", "lccN": 8352, "pages": 640, "lang": "eng", "holdings": 75, "cover": "mdp.39015074694764"}, {"title": "De poenale sanctie in de practijk.", "author": "Blankenstein, M. van 1880-", "id": "mdp.39015074695704", "lccA": "HV", "lccN": 8931, "pages": 96, "lang": "dut", "holdings": 16, "cover": "mdp.39015074695704"}, {"title": "Report of the Wisconsin Prison labor investigating committee.", "author": "Wisconsin. Legislature. Prison labor investigating committee.", "id": "mdp.39015074695720", "lccA": "HV", "lccN": 8929, "pages": 32, "lang": "eng", "holdings": 11, "cover": "mdp.39015074695720"}, {"title": "Annual report.", "author": "Massachusetts. Trustees of Massachusetts Training School.", "id": "mdp.39015074696207", "lccA": "HV", "lccN": 9105, "pages": 40, "lang": "eng", "holdings": 5, "cover": "mdp.39015074696207"}, {"title": "Report.", "author": "Whitten Village.", "id": "mdp.39015074701577", "lccA": "HV", "lccN": 3006, "pages": 24, "lang": "eng", "holdings": 2, "cover": "mdp.39015074701577"}, {"title": "Annual report.", "author": "Indiana. Boys' School, Plainfield.", "id": "mdp.39015074704225", "lccA": "HV", "lccN": 9105, "pages": 60, "lang": "eng", "holdings": 2, "cover": "mdp.39015074704225"}, {"title": "Annual police administration report of the Province of Bombay including railways.", "author": "Bombay (India : State). Police Department.", "id": "mdp.39015074706378", "lccA": "HV", "lccN": 7809, "pages": 150, "lang": "eng", "holdings": 2, "cover": "mdp.39015074706378"}, {"title": "Report.", "author": "New York (N.Y.). Department of Correction.", "id": "mdp.39015074707244", "lccA": "HV", "lccN": 8378, "pages": 188, "lang": "eng", "holdings": 4, "cover": "mdp.39015074707244"}, {"title": "Annual report of the inspectors.", "author": "State Penitentiary for the Eastern District of Pennsylvania.", "id": "mdp.39015074707400", "lccA": "HV", "lccN": 8358, "pages": 62, "lang": "eng", "holdings": 33, "cover": "mdp.39015074707400"}, {"title": "Annual report of the Orphan Section /", "author": "Duke Endowment. Orphan Section.", "id": "mdp.39015074709620", "lccA": "HV", "lccN": 990, "pages": 124, "lang": "eng", "holdings": 46, "cover": "mdp.39015074709620"}, {"title": "Annual report of the board of trustees and officers of the Indiana Soldiers' and Sailors' Children's Home for the fiscal year ending ... to the governor.", "author": "Indiana Soldiers' and Sailors' Children's Home.", "id": "mdp.39015074736185", "lccA": "HV", "lccN": 990, "pages": 62, "lang": "eng", "holdings": 13, "cover": "mdp.39015074736185"}, {"title": "Annual report.", "author": "New York State School for the Blind.", "id": "mdp.39015074803886", "lccA": "HV", "lccN": 1796, "pages": 28, "lang": "eng", "holdings": 3, "cover": "mdp.39015074803886"}, {"title": "Annual report of the Texas Prison System.", "author": "Texas. Prison Board.", "id": "mdp.39015074803985", "lccA": "HV", "lccN": 8363, "pages": 176, "lang": "eng", "holdings": 30, "cover": "mdp.39015074803985"}, {"title": "Annual report.", "author": "New York. State School, Rome.", "id": "mdp.39015076331522", "lccA": "HV", "lccN": 3006, "pages": 82, "lang": "eng", "holdings": 1, "cover": "mdp.39015076331522"}, {"title": "Abhandlungen aus dem Gesamtgebiete der Kriminalpsychologie:", "author": "", "id": "mdp.39015076352718", "lccA": "HV", "lccN": 6080, "pages": 484, "lang": "ger", "holdings": 44, "cover": "mdp.39015076352718"}, {"title": "Memorie autobiografiche /", "author": "Duval, Cl\u00e9ment, 1850-1935.", "id": "mdp.39015076846503", "lccA": "HV", "lccN": 9667, "pages": 1056, "lang": "ita", "holdings": 9, "cover": "mdp.39015076846503"}, {"title": "Tamn\u0101n r\u014dng l\u012bang dek kho\u0304\u031cng Phra\u02bbakkhrach\u0101y\u0101th\u0153\u0304 ... /", "author": "Damrongr\u0101ch\u0101nuph\u0101p, Prince, son of Mongkut, King of Siam, 1862-1943.", "id": "mdp.39015078082313", "lccA": "HV", "lccN": 1300, "pages": 74, "lang": "tha", "holdings": 2, "cover": "mdp.39015078082313"}, {"title": "Ch\u014dsen shakai jigy\u014d.", "author": "", "id": "mdp.39015079529213", "lccA": "HV", "lccN": 415, "pages": 302, "lang": "jpn", "holdings": 5, "cover": "mdp.39015079529213"}, {"title": "Scientific temperance journal.", "author": "", "id": "mdp.39015080096459", "lccA": "HV", "lccN": 5285, "pages": 64, "lang": "eng", "holdings": 22, "cover": "mdp.39015080096459"}, {"title": "The State trooper.", "author": "", "id": "mdp.39015080096475", "lccA": "HV", "lccN": 7451, "pages": 786, "lang": "eng", "holdings": 8, "cover": "mdp.39015080096475"}, {"title": "Proceedings of the annual meeting.", "author": "American Hearing Society.", "id": "mdp.39015080096863", "lccA": "HV", "lccN": 2522, "pages": 178, "lang": "eng", "holdings": 5, "cover": "mdp.39015080096863"}, {"title": "Advisory commission for the protection and welfare of children and young people.", "author": "League of Nations.", "id": "mdp.39015080165262", "lccA": "HV", "lccN": 703, "pages": 636, "lang": "eng", "holdings": 3, "cover": "mdp.39015080165262"}, {"title": "Advisory committee on traffic in opium and other dangerous drugs.", "author": "League of Nations.", "id": "mdp.39015080174280", "lccA": "HV", "lccN": 5816, "pages": 26, "lang": "eng", "holdings": 7, "cover": "mdp.39015080174280"}, {"title": "Quan guo jin yan hui yi hui bian /", "author": "Quan guo jin yan hui yi 1928 : Nanjing, Jiangsu Sheng, China), \u5168\u570b\u7981\u70df\u6703\u8b70 1928 : Nanjing, Jiangsu Sheng, China)", "id": "mdp.39015085379819", "lccA": "HV", "lccN": 5840, "pages": 284, "lang": "chi", "holdings": 5, "cover": "mdp.39015085379819"}, {"title": "Kodomo no seiki.", "author": "", "id": "mdp.39015097559176", "lccA": "HV", "lccN": 800, "pages": 392, "lang": "jpn", "holdings": 9, "cover": "mdp.39015097559176"}, {"title": "Report of the president & of the treasurer.", "author": "Carnegie Corporation of New York.", "id": "miua.0640577.1929.001", "lccA": "HV", "lccN": 97, "pages": 124, "lang": "eng", "holdings": 171, "cover": "miua.0640577.1929.001"}, {"title": "Crooks of the Waldorf, :", "author": "Smith, Horace Herbert, 1868-1936.", "id": "miua.0781766.0001.001", "lccA": "HV", "lccN": 7914, "pages": 330, "lang": "eng", "holdings": 25, "cover": "miua.0781766.0001.001"}, {"title": "Directory of social and health agencies of New York City.", "author": "", "id": "miun.aaf3120.1929.001", "lccA": "HV", "lccN": 99, "pages": 786, "lang": "eng", "holdings": 105, "cover": "miun.aaf3120.1929.001"}, {"title": "In the reign of Rothstein /", "author": "Clarke, Donald Henderson, 1887-1958.", "id": "miun.aev7523.0001.001", "lccA": "HV", "lccN": 6248, "pages": 328, "lang": "eng", "holdings": 83, "cover": "miun.aev7523.0001.001"}, {"title": "Traffic in opium and other dangerous drugs with respect to the Philippine islands ...", "author": "United States. Federal narcotic control board.", "id": "miun.ahj3222.1929.001", "lccA": "HV", "lccN": 5831, "pages": 24, "lang": "eng", "holdings": 44, "cover": "miun.ahj3222.1929.001"}, {"title": "Capital punishment in North Carolina.", "author": "North Carolina State Board of Public Welfare.", "id": "nc01.ark:/13960/t3fx8g49x", "lccA": "HV", "lccN": 86, "pages": 188, "lang": "eng", "holdings": 36, "cover": "nc01.ark:/13960/t3fx8g49x"}, {"title": "Biennial report of the Board of Trustees, Superintendent, and other officers of the Mississippi State Penitentiary.", "author": "Mississippi State Penitentiary.", "id": "nnc1.cu16132530", "lccA": "HV", "lccN": 8344, "pages": 168, "lang": "eng", "holdings": 23, "cover": "nnc1.cu16132530"}, {"title": "Report of the treasurer.", "author": "Carnegie Corporation of New York.", "id": "nnc2.ark:/13960/t0006m23v", "lccA": "HV", "lccN": 97, "pages": 38, "lang": "eng", "holdings": 9, "cover": "nnc2.ark:/13960/t0006m23v"}, {"title": "The New York Police College.", "author": "New York (N.Y.). Police Department.", "id": "nnc2.ark:/13960/t08w60t46", "lccA": "HV", "lccN": 8148, "pages": 56, "lang": "eng", "holdings": 6, "cover": "nnc2.ark:/13960/t08w60t46"}, {"title": "Carnegie Corporation Donations, Andrew Carnegie,", "author": "Carnegie Corporation of New York.", "id": "nnc2.ark:/13960/t4pk7dx53", "lccA": "HV", "lccN": 97, "pages": 174, "lang": "eng", "holdings": 2, "cover": "nnc2.ark:/13960/t4pk7dx53"}, {"title": "Carnegie Corporation Journal A,", "author": "Carnegie Corporation of New York.", "id": "nnc2.ark:/13960/t9g51r62g", "lccA": "HV", "lccN": 97, "pages": 486, "lang": "eng", "holdings": 2, "cover": "nnc2.ark:/13960/t9g51r62g"}, {"title": "Przegla\u0328d spo\u0142eczny :", "author": "", "id": "nyp.33433090159389", "lccA": "HV", "lccN": 1215, "pages": 526, "lang": "pol", "holdings": 2, "cover": "nyp.33433090159389"}, {"title": "Through a workhouse window,", "author": "Noordin, R. M., 1902-", "id": "nyp.33433100076631", "lccA": "HV", "lccN": 245, "pages": 232, "lang": "eng", "holdings": 18, "cover": "nyp.33433100076631"}, {"title": "La delincuencia femenina en Cuba ...", "author": "Castellanos, Israel, 1891-1977.", "id": "nyp.33433100315591", "lccA": "HV", "lccN": 6858, "pages": 446, "lang": "spa", "holdings": 15, "cover": "nyp.33433100315591"}, {"title": "Wohlfahrts- und jugendamt der landeshauptstadt Mu\u0308nchen nach dem weltkriege :", "author": "Munich (Germany). Sta\u0308dtisches Wohlfahrts- und Jugendamt.", "id": "osu.32435002322758", "lccA": "HV", "lccN": 280, "pages": 226, "lang": "ger", "holdings": 5, "cover": "osu.32435002322758"}, {"title": "Survey of type jobs in the printing industry as carried on by the Olsen Printing and Publishing Company.", "author": "Wisconsin. State Board of Vocational and Adult Education. Rehabilitation Division.", "id": "osu.32435005103569", "lccA": "HV", "lccN": 3019, "pages": 42, "lang": "eng", "holdings": 1, "cover": "osu.32435005103569"}, {"title": "The Luella Hannan memorial home, a living remembrance of William W. and Luella Hannan .", "author": "Luella Hannan Memorial Home (Detroit, Mich.)", "id": "osu.32435005226378", "lccA": "HV", "lccN": 99, "pages": 20, "lang": "eng", "holdings": 10, "cover": "osu.32435005226378"}, {"title": "Survey of type jobs in the knitting industry as carried on by the National Knitting Company.", "author": "Wisconsin. State Board of Vocational and Adult Education. Rehabilitation Division.", "id": "osu.32435005316518", "lccA": "HV", "lccN": 3019, "pages": 58, "lang": "eng", "holdings": 1, "cover": "osu.32435005316518"}, {"title": "Survey of type jobs in the clothing manufacturing industry as carried on by the David Adler and company.", "author": "Wisconsin. State board of vocational & adult education. Rehabilitation division.", "id": "osu.32435007545254", "lccA": "HV", "lccN": 3019, "pages": 94, "lang": "eng", "holdings": 1, "cover": "osu.32435007545254"}, {"title": "Survey of type jobs in the hose manufacturing industry as carried on by the Holeproof Hosiery Company.", "author": "Wisconsin. State Board of Vocational and Adult Education. Rehabilitation Division.", "id": "osu.32435008133704", "lccA": "HV", "lccN": 3019, "pages": 56, "lang": "eng", "holdings": 1, "cover": "osu.32435008133704"}, {"title": "Survey of type jobs in the candy manufacturing industry as carried on by the Robert A. Johnston candy company.", "author": "Wisconsin. State Board of Vocational and Adult Education. Rehabilitation Division.", "id": "osu.32435008347247", "lccA": "HV", "lccN": 3019, "pages": 84, "lang": "eng", "holdings": 1, "cover": "osu.32435008347247"}, {"title": "Reconstruction and prohibition /", "author": "Lowell, A. Lawrence 1856-1943.", "id": "osu.32435008660763", "lccA": "HV", "lccN": 5089, "pages": 16, "lang": "eng", "holdings": 9, "cover": "osu.32435008660763"}, {"title": "Survey of type jobs in the box manufacturing industry as carried on by the Molitor box company.", "author": "Wisconsin. State Board of Vocational and Adult Education. Rehabilitation Division.", "id": "osu.32435008782260", "lccA": "HV", "lccN": 3019, "pages": 54, "lang": "eng", "holdings": 1, "cover": "osu.32435008782260"}, {"title": "Survey of type jobs in the engraving industry as carried on by the Badger Engraving Company.", "author": "Wisconsin. State Board of Vocational and Adult Education. Rehabilitation Division.", "id": "osu.32435009874397", "lccA": "HV", "lccN": 3019, "pages": 30, "lang": "eng", "holdings": 1, "cover": "osu.32435009874397"}, {"title": "Toledo social workers :", "author": "Toledo Consumers' League (Ohio)", "id": "osu.32435010099687", "lccA": "HV", "lccN": 99, "pages": 78, "lang": "eng", "holdings": 3, "cover": "osu.32435010099687"}, {"title": "Research recommendations of the second Conference on Problems of the Deaf and Hard of Hearing, Washington, D.C., February 1 and 2, 1929.", "author": "Conference on Problems of the Deaf and Hard of Hearing 1929) Washington, D.C.)", "id": "osu.32435012483160", "lccA": "HV", "lccN": 2526, "pages": 68, "lang": "eng", "holdings": 29, "cover": "osu.32435012483160"}, {"title": "The prisoner's antecedents.", "author": "United States. Bureau of the Census.", "id": "osu.32435012765780", "lccA": "HV", "lccN": 7248, "pages": 24, "lang": "eng", "holdings": 33, "cover": "osu.32435012765780"}, {"title": "Survey of type jobs in the stationery engraving industry and the watch repairing and jewelry manufacturing industry as carried on by the Bunde and Epmeyer Company.", "author": "Wisconsin. State Board of Vocational and Adult Education. Rehabilitation Division.", "id": "osu.32435013460019", "lccA": "HV", "lccN": 3019, "pages": 38, "lang": "eng", "holdings": 2, "cover": "osu.32435013460019"}, {"title": "Suggestions for motivating primary braille reading /", "author": "Merry, Frieda Kiefer.", "id": "osu.32435013592282", "lccA": "HV", "lccN": 1672, "pages": 42, "lang": "eng", "holdings": 6, "cover": "osu.32435013592282"}, {"title": "Theory of prohibition /", "author": "Cobb, Sanford H. 1838-1910.", "id": "osu.32435014671234", "lccA": "HV", "lccN": 5089, "pages": 16, "lang": "eng", "holdings": 4, "cover": "osu.32435014671234"}, {"title": "\"Charities and corrections\", Jackson county, Missouri. :", "author": "Kansas City Public Service Institute.", "id": "osu.32435015290323", "lccA": "HV", "lccN": 98, "pages": 520, "lang": "eng", "holdings": 1, "cover": "osu.32435015290323"}, {"title": "Survey of type jobs in the shoe manufacturing industry as carried on by the Nunn-Busch shoe factory.", "author": "Wisconsin. State Board of Vocational and Adult Education. Rehabilitation Division.", "id": "osu.32435015599863", "lccA": "HV", "lccN": 3019, "pages": 100, "lang": "eng", "holdings": 1, "cover": "osu.32435015599863"}, {"title": "The probation officer and the community /", "author": "Lundberg, Emma O.", "id": "osu.32435016892960", "lccA": "HV", "lccN": 9301, "pages": 12, "lang": "eng", "holdings": 7, "cover": "osu.32435016892960"}, {"title": "The New England flood disaster, November, 1927.", "author": "American National Red Cross.", "id": "osu.32435020931663", "lccA": "HV", "lccN": 575, "pages": 26, "lang": "eng", "holdings": 13, "cover": "osu.32435020931663"}, {"title": "Proceedings of the annual meeting.", "author": "National Conference of Catholic Charities (U.S.)", "id": "osu.32435024168569", "lccA": "HV", "lccN": 88, "pages": 268, "lang": "eng", "holdings": 105, "cover": "osu.32435024168569"}, {"title": "Annual report of the State Department of Public Welfare of Virginia.", "author": "Virginia. Department of Public Welfare.", "id": "osu.32435051126449", "lccA": "HV", "lccN": 86, "pages": 152, "lang": "eng", "holdings": 13, "cover": "osu.32435051126449"}, {"title": "Annual statistical review.", "author": "Illinois. Department of Public Welfare.", "id": "osu.32435051191013", "lccA": "HV", "lccN": 98, "pages": 282, "lang": "eng", "holdings": 36, "cover": "osu.32435051191013"}, {"title": "Annual report /", "author": "Illinois. Dept. of Public Welfare.", "id": "osu.32435051191484", "lccA": "HV", "lccN": 86, "pages": 544, "lang": "eng", "holdings": 61, "cover": "osu.32435051191484"}, {"title": "Report of the State Board of Charities and Corrections of the Commonwelath of Kentucky.", "author": "Kentucky. State Board of Charities and Corrections.", "id": "osu.32435051193738", "lccA": "HV", "lccN": 86, "pages": 150, "lang": "eng", "holdings": 30, "cover": "uc1.b2881751"}, {"title": "Grants, fellowships and certain other appropriations in ... /", "author": "Milbank Memorial Fund.", "id": "osu.32435051641587", "lccA": "HV", "lccN": 97, "pages": 98, "lang": "eng", "holdings": 20, "cover": "osu.32435051641587"}, {"title": "Bulletin of the National Conference of Charities and Correction.", "author": "National Conference of Charities and Correction (U.S.)", "id": "osu.32435053916409", "lccA": "HV", "lccN": 88, "pages": 176, "lang": "eng", "holdings": 29, "cover": "osu.32435053916409"}, {"title": "Annual report of the Commissioner /", "author": "Albany (N.Y.). Department of Public Safety.", "id": "osu.32435054343041", "lccA": "HV", "lccN": 7575, "pages": 92, "lang": "eng", "holdings": 10, "cover": "osu.32435054343041"}, {"title": "The child, the family, and the court:", "author": "Flexner, Bernard, 1865-1945.", "id": "osu.32435061566014", "lccA": "HV", "lccN": 741, "pages": 844, "lang": "eng", "holdings": 11, "cover": "osu.32435061566014"}, {"title": "Quarterly bulletin.", "author": "Managing Officers' Association (Ohio)", "id": "osu.32435063612899", "lccA": "HV", "lccN": 86, "pages": 132, "lang": "eng", "holdings": 12, "cover": "osu.32435063612899"}, {"title": "Annual report of Perkins Institution and Massachusetts School for the Blind.", "author": "Perkins Institution and Massachusetts School for the Blind.", "id": "osu.32435063625719", "lccA": "HV", "lccN": 1796, "pages": 450, "lang": "eng", "holdings": 36, "cover": "osu.32435063625719"}, {"title": "The industrial school journal.", "author": "", "id": "osu.32435063903850", "lccA": "HV", "lccN": 9051, "pages": 820, "lang": "eng", "holdings": 3, "cover": "osu.32435063903850"}, {"title": "Annual report .", "author": "Ohio. Board of Clemency.", "id": "osu.32435063991335", "lccA": "HV", "lccN": 8355, "pages": 28, "lang": "eng", "holdings": 6, "cover": "osu.32435063991335"}, {"title": "Annual report.", "author": "American Anti-Vivisection Society.", "id": "osu.32435064001332", "lccA": "HV", "lccN": 4926, "pages": 52, "lang": "eng", "holdings": 25, "cover": "osu.32435064001332"}, {"title": "When disaster strikes :", "author": "American National Red Cross.", "id": "osu.32435067031005", "lccA": "HV", "lccN": 575, "pages": 40, "lang": "eng", "holdings": 13, "cover": "osu.32435067031005"}, {"title": "States laws and local ordinances regulating the street work of children :", "author": "United States. Children's Bureau.", "id": "osu.32435067631887", "lccA": "HV", "lccN": 741, "pages": 36, "lang": "eng", "holdings": 7, "cover": "osu.32435067631887"}, {"title": "Chart series.", "author": "United States. Children's Bureau.", "id": "osu.32435067640573", "lccA": "HV", "lccN": 741, "pages": 60, "lang": "eng", "holdings": 11, "cover": "osu.32435067640573"}, {"title": "Prison industries.", "author": "United States. Department of Commerce. Advisory committee on prison industries.", "id": "osu.32435070896360", "lccA": "HV", "lccN": 8923, "pages": 150, "lang": "eng", "holdings": 47, "cover": "osu.32435070896360"}, {"title": "The Bank of England forgery /", "author": "", "id": "osu.32437000339917", "lccA": "HV", "lccN": 6771, "pages": 344, "lang": "eng", "holdings": 55, "cover": "osu.32437000339917"}, {"title": "Curious punishments of bygone days /", "author": "Earle, Alice Morse, 1851-1911.", "id": "pst.000001182927", "lccA": "HV", "lccN": 8532, "pages": 170, "lang": "eng", "holdings": 51, "cover": "pst.000001182927"}, {"title": "The Bureau of Prohibition :", "author": "Schmeckebier, Laurence Frederick, 1877-1959.", "id": "pst.000010590225", "lccA": "HV", "lccN": 5089, "pages": 360, "lang": false, "holdings": null, "cover": "pst.000010590225"}, {"title": "Statewide welfare agencies in Pennsylvania :", "author": "Blair, J. J.", "id": "pst.000018448979", "lccA": "HV", "lccN": 98, "pages": 52, "lang": "eng", "holdings": 4, "cover": "pst.000018448979"}, {"title": "Carnegie Hero Fund Commission.", "author": "Carnegie Hero Fund Commission.", "id": "pst.000019507521", "lccA": "HV", "lccN": 670, "pages": 104, "lang": "eng", "holdings": 219, "cover": "pst.000019507521"}, {"title": "The newer method in speech reading for the hard of hearing child :", "author": "Whilin, Olive Aida.", "id": "pst.000057401379", "lccA": "HV", "lccN": 2487, "pages": 160, "lang": "eng", "holdings": 24, "cover": "pst.000057401379"}, {"title": "Bulletin.", "author": "Pennsylvania. Dept. of Public Welfare.", "id": "pst.000061784840", "lccA": "HV", "lccN": 86, "pages": 28, "lang": "eng", "holdings": 17, "cover": "pst.000061784840"}, {"title": "Annual report of the Indiana School for Feeble-Minded Youth, Ft. Wayne, Indiana, for the fiscal year ending October 31 ..", "author": "Indiana School for Feeble-Minded Youth.", "id": "pur1.32754086694720", "lccA": "HV", "lccN": 3006, "pages": 60, "lang": "eng", "holdings": 17, "cover": "pur1.32754086694720"}, {"title": "Cain;", "author": "Godwin, George, 1889-1974.", "id": "uc1.$b194165", "lccA": "HV", "lccN": 6025, "pages": 118, "lang": "eng", "holdings": 37, "cover": "uc1.$b194165"}, {"title": "The profession of social work.", "author": "Bruno, Frank John, 1874-1955.", "id": "uc1.$b194192", "lccA": "HV", "lccN": 10, "pages": 10, "lang": "eng", "holdings": 6, "cover": "uc1.$b194192"}, {"title": "Emily Hobhouse;", "author": "Hobhouse, Emily, 1860-1926.", "id": "uc1.$b194256", "lccA": "HV", "lccN": 28, "pages": 344, "lang": "eng", "holdings": 48, "cover": "uc1.$b194256"}, {"title": "The diary of a rum-runner,", "author": "Moray, Alastair", "id": "uc1.$b19528", "lccA": "HV", "lccN": 5089, "pages": 326, "lang": "eng", "holdings": 26, "cover": "uc1.$b19528"}, {"title": "Gemeinde Wien und bundespolizei.", "author": "Brockhausen, Karl, 1859-", "id": "uc1.$b19636", "lccA": "HV", "lccN": 8202, "pages": 16, "lang": "ger", "holdings": 4, "cover": "uc1.$b19636"}, {"title": "Health and medical service in American prisons and reformatories,", "author": "Rector, Frank Leslie, 1879-", "id": "uc1.$b19648", "lccA": "HV", "lccN": 8833, "pages": 300, "lang": "eng", "holdings": 118, "cover": "uc1.$b19648"}, {"title": "Luis Candelas,", "author": "Espina, Antonio, 1894-1972.", "id": "uc1.$b196625", "lccA": "HV", "lccN": 6248, "pages": 280, "lang": "spa", "holdings": 34, "cover": "uc1.$b196625"}, {"title": "Masterstrokes of crime detection /", "author": "Wren, Lassiter.", "id": "uc1.$b20307", "lccA": "HV", "lccN": 6016, "pages": 280, "lang": "eng", "holdings": 59, "cover": "uc1.$b20307"}, {"title": "Chicago gang land;", "author": "Bennett, James O'Donnell, 1870-1940.", "id": "uc1.$b20513", "lccA": "HV", "lccN": 6795, "pages": 104, "lang": "eng", "holdings": 24, "cover": "uc1.$b20513"}, {"title": "Community councils in action;", "author": "Dunham, Arthur, 1893-", "id": "uc1.$b21605", "lccA": "HV", "lccN": 41, "pages": 36, "lang": "eng", "holdings": 12, "cover": "uc1.$b21605"}, {"title": "Great crimes of the West,", "author": "Fanning, Peter.", "id": "uc1.$b251009", "lccA": "HV", "lccN": 6783, "pages": 306, "lang": "eng", "holdings": 86, "cover": "uc1.$b251009"}, {"title": "The Catholic church and the destitute,", "author": "O'Grady, John, 1886-1966.", "id": "uc1.$b266116", "lccA": "HV", "lccN": 530, "pages": 152, "lang": "eng", "holdings": 121, "cover": "uc1.$b266116"}, {"title": "The treatment of the sick poor of this country and the preservation of the health of the poor in this country,", "author": "McCurrich, Hugh James", "id": "uc1.$b266157", "lccA": "HV", "lccN": 245, "pages": 144, "lang": "eng", "holdings": 23, "cover": "uc1.$b266157"}, {"title": "Drink: coercion or control?", "author": "Dorr, Rheta Childe, 1866-1948.", "id": "uc1.$b268511", "lccA": "HV", "lccN": 5082, "pages": 348, "lang": "eng", "holdings": 80, "cover": "uc1.$b268511"}, {"title": "Temperance--or prohibition?", "author": "Hearst Temperance Contest Committee.", "id": "uc1.$b268693", "lccA": "HV", "lccN": 5089, "pages": 436, "lang": "eng", "holdings": 136, "cover": "uc1.$b268693"}, {"title": "Practical prohibition.", "author": "Grubbs, Vincent W. 1848-", "id": "uc1.$b268697", "lccA": "HV", "lccN": 5089, "pages": 398, "lang": "eng", "holdings": 26, "cover": "uc1.$b268697"}, {"title": "Give prohibition its chance /", "author": "Boole, Ella A. 1858-1952.", "id": "uc1.$b268699", "lccA": "HV", "lccN": 5089, "pages": 198, "lang": "eng", "holdings": 74, "cover": "uc1.$b268699"}, {"title": "Philosophy of the dusk,", "author": "O'Dare, Kain.", "id": "uc1.$b268967", "lccA": "HV", "lccN": 6248, "pages": 284, "lang": "eng", "holdings": 43, "cover": "uc1.$b268967"}, {"title": "Dramatic days at the Old Bailey,", "author": "Kingston, Charles.", "id": "uc1.$b269195", "lccA": "HV", "lccN": 6950, "pages": 352, "lang": "eng", "holdings": 8, "cover": "uc1.$b269195"}, {"title": "Guia de te\u0301cnica policial.", "author": "Pessoa, Alberto.", "id": "uc1.$b269222", "lccA": "HV", "lccN": 8073, "pages": 224, "lang": "por", "holdings": 4, "cover": "uc1.$b269222"}, {"title": "Police and public,", "author": "Wright, S. Fowler 1874-1965.", "id": "uc1.$b269314", "lccA": "HV", "lccN": 8195, "pages": 152, "lang": "eng", "holdings": 20, "cover": "uc1.$b269314"}, {"title": "On the trail of the little white imp;", "author": "Rutherford, Mac B., 1877-", "id": "uc1.$b28082", "lccA": "HV", "lccN": 5740, "pages": 68, "lang": "eng", "holdings": 3, "cover": "uc1.$b28082"}, {"title": "The mystery of Jack the Ripper;", "author": "Matters, Leonard.", "id": "uc1.$b313869", "lccA": "HV", "lccN": 6535, "pages": 278, "lang": "eng", "holdings": 23, "cover": "uc1.$b313869"}, {"title": "The Catholic charities review.", "author": "", "id": "uc1.$b357759", "lccA": "HV", "lccN": 1, "pages": 406, "lang": "eng", "holdings": 140, "cover": "uc1.$b357759"}, {"title": "The Social service review", "author": "", "id": "uc1.$b357930", "lccA": "HV", "lccN": 1, "pages": 756, "lang": "eng", "holdings": 771, "cover": "uc1.$b357930"}, {"title": "Le banquier de Pontoise et les vrais myst\u00e8res de Paris.", "author": "Bouchardon, Pierre, b. 1870.", "id": "uc1.$b382007", "lccA": "HV", "lccN": 6248, "pages": 272, "lang": "fre", "holdings": 6, "cover": "uc1.$b382007"}, {"title": "Crimes of violence and revenge,", "author": "Ashton-Wolfe, Harry, 1881-", "id": "uc1.$b382265", "lccA": "HV", "lccN": 6245, "pages": 398, "lang": "eng", "holdings": 62, "cover": "uc1.$b382265"}, {"title": "\"His majesty's guests\" :", "author": "", "id": "uc1.$b384047", "lccA": "HV", "lccN": 9346, "pages": 268, "lang": "eng", "holdings": 28, "cover": "uc1.$b384047"}, {"title": "Boleti\u0301n del Instituto Internacional Americano de Proteccio\u0301n a la Infancia.", "author": "Interamerican Children's Institute.", "id": "uc1.$b446177", "lccA": "HV", "lccN": 703, "pages": 420, "lang": "eng", "holdings": 45, "cover": "uc1.$b446177"}, {"title": "Probation: its aims, methods and limitations", "author": "Parsons, Herbert Collins, 1862-1941.", "id": "uc1.$b50234", "lccA": "HV", "lccN": 9278, "pages": 24, "lang": "eng", "holdings": 7, "cover": "uc1.$b50234"}, {"title": "The invisible web;", "author": "Ashton-Wolfe, Harry, 1881-", "id": "uc1.$b50249", "lccA": "HV", "lccN": 6970, "pages": 326, "lang": "eng", "holdings": 31, "cover": "uc1.$b50249"}, {"title": "The social worker in group work,", "author": "Williamson, Margaretta A., 1891-", "id": "uc1.$b55712", "lccA": "HV", "lccN": 40, "pages": 272, "lang": "eng", "holdings": 161, "cover": "uc1.$b55712"}, {"title": "Revue internationale de criminalistique", "author": "", "id": "uc1.$b597521", "lccA": "HV", "lccN": 6001, "pages": 752, "lang": false, "holdings": null, "cover": "uc1.$b597521"}, {"title": "The British journal of inebriety.", "author": "", "id": "uc1.$b597964", "lccA": "HV", "lccN": 5800, "pages": 304, "lang": "eng", "holdings": 60, "cover": "uc1.$b597964"}, {"title": "Archiv fu\u0308r kriminologie.", "author": "", "id": "uc1.$b598014", "lccA": "HV", "lccN": 6003, "pages": 600, "lang": "ger", "holdings": 58, "cover": "ufl.31262098813719"}, {"title": "Annual report - The American National Red Cross.", "author": "American National Red Cross.", "id": "uc1.$b599341", "lccA": "HV", "lccN": 575, "pages": 220, "lang": "eng", "holdings": 223, "cover": "uc1.$b599341"}, {"title": "Outlook for the blind.", "author": "", "id": "uc1.$b599606", "lccA": "HV", "lccN": 1571, "pages": 554, "lang": "eng", "holdings": 72, "cover": "uc1.$b599606"}, {"title": "The Journal of Juvenile Research", "author": "", "id": "uc1.$b599868", "lccA": "HV", "lccN": 6001, "pages": 336, "lang": false, "holdings": null, "cover": "uc1.$b599868"}, {"title": "Annual Report", "author": "Charity Organization Society of Buffalo", "id": "uc1.$b600491", "lccA": "HV", "lccN": 99, "pages": 128, "lang": false, "holdings": null, "cover": "uc1.$b600491"}, {"title": "Proceedings.", "author": "National Conference on Social Welfare (U.S.)", "id": "uc1.$b603115", "lccA": "HV", "lccN": 88, "pages": 702, "lang": "eng", "holdings": 10, "cover": "uc1.$b603115"}, {"title": "The Training school bulletin.", "author": "", "id": "uc1.$b609201", "lccA": "HV", "lccN": 897, "pages": 196, "lang": "eng", "holdings": 232, "cover": "uc1.$b609201"}, {"title": "The malavites,", "author": "Gettys, Warner E. b. 1891.", "id": "uc1.$b731995", "lccA": "HV", "lccN": 1555, "pages": 24, "lang": "eng", "holdings": 16, "cover": "uc1.$b731995"}, {"title": "Adventures of an outlaw,", "author": "Tucker, James, 1808?-1888?", "id": "uc1.$b812002", "lccA": "HV", "lccN": 6248, "pages": 384, "lang": "eng", "holdings": 4, "cover": "uc1.$b812002"}, {"title": "Some aspects of relief in family casework;", "author": "Marcus, Grace Florence, 1893-", "id": "uc1.$b99376", "lccA": "HV", "lccN": 40, "pages": 170, "lang": "eng", "holdings": 165, "cover": "uc1.$b99376"}, {"title": "Counties in transition, a study of county public and private welfare administration in Virginia", "author": "Hoffer, Frank William.", "id": "uc1.$b99527", "lccA": "HV", "lccN": 98, "pages": 288, "lang": "eng", "holdings": 115, "cover": "uc1.$b99527"}, {"title": "Report.", "author": "Missouri. Department of Penal Institutions.", "id": "uc1.31158005444731", "lccA": "HV", "lccN": 8345, "pages": 734, "lang": "eng", "holdings": 29, "cover": "uc1.31158005444731"}, {"title": "La delincuencia feminina en Cuba :", "author": "Castellanos, Israel, 1891-1977", "id": "uc1.31210010032900", "lccA": "HV", "lccN": 6046, "pages": 584, "lang": "spa", "holdings": 7, "cover": "uc1.31210010032900"}, {"title": "Handbook of American prisons and reformatories, 1929 /", "author": "", "id": "uc1.31822019535202", "lccA": "HV", "lccN": 9471, "pages": 1092, "lang": "eng", "holdings": 27, "cover": "uc1.31822019535202"}, {"title": "Barmaids :", "author": "", "id": "uc1.31822031024771", "lccA": "HV", "lccN": 5443, "pages": 20, "lang": "eng", "holdings": 1, "cover": "uc1.31822031024771"}, {"title": "Oklahombres :", "author": "Nix, Evett Dumas, 1861-1946", "id": "uc1.31822042769398", "lccA": "HV", "lccN": 6793, "pages": 352, "lang": "eng", "holdings": 129, "cover": "uc1.31822042769398"}, {"title": "Sterilization for human betterment;", "author": "Gosney, E. S. 1855-1942.", "id": "uc1.32106005425100", "lccA": "HV", "lccN": 4989, "pages": 236, "lang": "eng", "holdings": 207, "cover": "uc1.32106005425100"}, {"title": "Social work year book", "author": "", "id": "uc1.32106008546381", "lccA": "HV", "lccN": 35, "pages": 612, "lang": "eng", "holdings": 355, "cover": "uc1.32106008546381"}, {"title": "A hangman's diary, being the journal of Master Franz Schmidt, public executioner of Nuremberg, 1573-1617,", "author": "Schmidt, Franz, d. 1634.", "id": "uc1.32106010138433", "lccA": "HV", "lccN": 8579, "pages": 288, "lang": "eng", "holdings": 5, "cover": "uc1.32106010138433"}, {"title": "Die Wohlfahrtspflege der Stadt Z\u00fcrich seit 1893;", "author": "Legler, Angelika, 1897-", "id": "uc1.b2648527", "lccA": "HV", "lccN": 355, "pages": 342, "lang": "ger", "holdings": 11, "cover": "uc1.b2648527"}, {"title": "Annual Report", "author": "New York (State). Board of Social Welfare.", "id": "uc1.b2881825", "lccA": "HV", "lccN": 86, "pages": 320, "lang": false, "holdings": null, "cover": "uc1.b2881825"}, {"title": "Encyclopedia of social work.", "author": "", "id": "uc1.b2900405", "lccA": "HV", "lccN": 35, "pages": 644, "lang": "eng", "holdings": 281, "cover": "uc1.b2900405"}, {"title": "The state of corrections.", "author": "American Correctional Association.", "id": "uc1.b2970558", "lccA": "HV", "lccN": 8987, "pages": 424, "lang": "eng", "holdings": 4, "cover": "uc1.b2970558"}, {"title": "Annual report of the Board of Welfare.", "author": "Maryland. Board of Welfare.", "id": "uc1.b2995778", "lccA": "HV", "lccN": 86, "pages": 1012, "lang": "eng", "holdings": 29, "cover": "uc1.b2995778"}, {"title": "Report.", "author": "Perkins School for the Blind.", "id": "uc1.b2996708", "lccA": "HV", "lccN": 1796, "pages": 450, "lang": "eng", "holdings": 34, "cover": "uc1.b2996708"}, {"title": "Annual Report", "author": "Philippines. Bureau of Public Welfare.", "id": "uc1.b2996729", "lccA": "HV", "lccN": 406, "pages": 282, "lang": false, "holdings": null, "cover": "uc1.b2996729"}, {"title": "Report", "author": "Mississippi State Penitentiary.", "id": "uc1.b2997571", "lccA": "HV", "lccN": 8344, "pages": 190, "lang": false, "holdings": null, "cover": "uc1.b2997571"}, {"title": "Annual Report", "author": "Rhode Island. State Public Welfare Commission.", "id": "uc1.b2997574", "lccA": "HV", "lccN": 86, "pages": 402, "lang": false, "holdings": null, "cover": "uc1.b2997574"}, {"title": "Report", "author": "New York (State). Division of Probation.", "id": "uc1.b3001024", "lccA": "HV", "lccN": 9305, "pages": 234, "lang": false, "holdings": null, "cover": "uc1.b3001024"}, {"title": "Hospital social service", "author": "", "id": "uc1.b3018525", "lccA": "HV", "lccN": 687, "pages": 686, "lang": false, "holdings": null, "cover": "uc1.b3018525"}, {"title": "Die Alkoholfrage.", "author": "", "id": "uc1.b3018553", "lccA": "HV", "lccN": 5001, "pages": 388, "lang": "ger", "holdings": 20, "cover": "uc1.b3018553"}, {"title": "Biennial report of the Missouri School for the Blind to the ... General Assembly.", "author": "Missouri School for the Blind.", "id": "uc1.b3025451", "lccA": "HV", "lccN": 1796, "pages": 578, "lang": "eng", "holdings": 9, "cover": "uc1.b3025451"}, {"title": "Sivilrettsstatistikk.", "author": "", "id": "uc1.b3099992", "lccA": "HV", "lccN": 7359, "pages": 40, "lang": "nor", "holdings": 3, "cover": "uc1.b3099992"}, {"title": "Report", "author": "Buhl Foundation.", "id": "uc1.b3102918", "lccA": "HV", "lccN": 99, "pages": 280, "lang": false, "holdings": null, "cover": "uc1.b3102918"}, {"title": "Report of the Royal commission on police powers and procedure.", "author": "Great Britain. Royal Commission on Police Powers and Procedure.", "id": "uc1.b3113320", "lccA": "HV", "lccN": 7725, "pages": 180, "lang": "eng", "holdings": 28, "cover": "uc1.b3113320"}, {"title": "Organized crime in Chicago.", "author": "Landesco, John.", "id": "uc1.b3115060", "lccA": "HV", "lccN": 6795, "pages": 300, "lang": "eng", "holdings": 20, "cover": "uc1.b3115060"}, {"title": "Zum selbstmord problem,", "author": "Rehfeldt,.", "id": "uc1.b3132523", "lccA": "HV", "lccN": 6545, "pages": 32, "lang": "ger", "holdings": 2, "cover": "uc1.b3132523"}, {"title": "Public welfare:", "author": "Georgia. Board of Public Welfare.", "id": "uc1.b3170566", "lccA": "HV", "lccN": 86, "pages": 40, "lang": "eng", "holdings": 15, "cover": "uc1.b3170566"}, {"title": "Der Verbrecher und seine Richter;", "author": "Alexander, Franz, 1891-1964.", "id": "uc1.b3224652", "lccA": "HV", "lccN": 6080, "pages": 136, "lang": "ger", "holdings": 52, "cover": "uc1.b3224652"}, {"title": "The Milbank Memorial Fund quarterly bulletin.", "author": "", "id": "uc1.b3330528", "lccA": "HV", "lccN": 97, "pages": 588, "lang": "eng", "holdings": 166, "cover": "uc1.b3330528"}, {"title": "Poverty,", "author": "Kelso, Robert W. 1880-1966.", "id": "uc1.b3386811", "lccA": "HV", "lccN": 31, "pages": 392, "lang": "eng", "holdings": 239, "cover": "uc1.b3386811"}, {"title": "The diary of a rum-runner,", "author": "Moray, Alastair", "id": "uc1.b3386847", "lccA": "HV", "lccN": 5089, "pages": 322, "lang": "eng", "holdings": 28, "cover": "uc1.b3386847"}, {"title": "The adventures of Ralph Rashleigh;", "author": "Rashleigh, Ralph.", "id": "uc1.b3386864", "lccA": "HV", "lccN": 6248, "pages": 374, "lang": "eng", "holdings": 50, "cover": "uc1.b3386864"}, {"title": "Proceedings of the National Conference of Social Work at the ... Annual Session held in ..", "author": "National Conference of Social Work (U.S.). Session.", "id": "uc1.b3623269", "lccA": "HV", "lccN": 88, "pages": 702, "lang": "eng", "holdings": 190, "cover": "uc1.b3623269"}, {"title": "Poverty,", "author": "Kelso, Robert W. 1880-1966.", "id": "uc1.b3626430", "lccA": "HV", "lccN": 31, "pages": 396, "lang": "eng", "holdings": 239, "cover": "uc1.b3626430"}, {"title": "The Family.", "author": "", "id": "uc1.b3641605", "lccA": "HV", "lccN": 1, "pages": 372, "lang": "eng", "holdings": 951, "cover": "uc1.b3641605"}, {"title": "Handelingen.", "author": "Nederlandse Vereniging Sociale Zorg voor Minder-Validen \"Actio Vincit Omnia\" (1928 : Amsterdam)", "id": "uc1.b3646095", "lccA": "HV", "lccN": 307, "pages": 1268, "lang": "dut", "holdings": 3, "cover": "uc1.b3646095"}, {"title": "Days of fear,", "author": "Gallagher, Frank.", "id": "uc1.b4072775", "lccA": "HV", "lccN": 9650, "pages": 182, "lang": "eng", "holdings": 48, "cover": "uc1.b4072775"}, {"title": "Endocrinologia y criminalidad.", "author": "Ruiz-Funes Garci\u0301a, Mariano, 1889-1953.", "id": "uc1.b4498956", "lccA": "HV", "lccN": 6143, "pages": 384, "lang": "spa", "holdings": 12, "cover": "uc1.b4498956"}, {"title": "Annual report of the Police Commissioner for the City of Boston.", "author": "Boston (Mass.). Office of the Police Commissioner.", "id": "uc1.b4525778", "lccA": "HV", "lccN": 7578, "pages": 88, "lang": "eng", "holdings": 26, "cover": "uc1.b4525778"}, {"title": "Annual report of the Board of Directors and Superintendent of the South Carolina Penitentiary .", "author": "South Carolina Penitentiary. Board of Directors.", "id": "uc1.b4628548", "lccA": "HV", "lccN": 8360, "pages": 872, "lang": "eng", "holdings": 15, "cover": "uc1.b4628548"}, {"title": "Orlovski\u012d katorzhny\u012d t\ufe20s\ufe21entral :", "author": "", "id": "uc1.b5074712", "lccA": "HV", "lccN": 6295, "pages": 232, "lang": "rus", "holdings": 5, "cover": "uc1.b5074712"}, {"title": "Outlaw trails;", "author": "Witten, George.", "id": "uc1.c035324631", "lccA": "HV", "lccN": 4505, "pages": 286, "lang": "eng", "holdings": 31, "cover": "uc1.c035324631"}, {"title": "Ten real murder mysteries /", "author": "Sutherland, Sidney, 1888-", "id": "uc1.c045446429", "lccA": "HV", "lccN": 6524, "pages": 374, "lang": "eng", "holdings": 27, "cover": "uc1.c045446429"}, {"title": "Fur\u014dsha ni kansuru ch\u014dsa, jid\u014d renk\u014d no kojiki ni kansuru ch\u014dsa.", "author": "", "id": "uc1.c067471551", "lccA": "HV", "lccN": 4607, "pages": 156, "lang": "jpn", "holdings": 3, "cover": "uc1.c067471551"}, {"title": "Report.", "author": "Royal National Institute for the Blind.", "id": "uc1.c2550116", "lccA": "HV", "lccN": 1573, "pages": 72, "lang": "eng", "holdings": 3, "cover": "uc1.c2550116"}, {"title": "The National humane review /", "author": "", "id": "uc1.c2559534", "lccA": "HV", "lccN": 4701, "pages": 574, "lang": "eng", "holdings": 50, "cover": "uc1.c2559534"}, {"title": "Report on the administration of jails of the province of Bengal.", "author": "Bengal (India). Jail Dept.", "id": "uc1.d0000652826", "lccA": "HV", "lccN": 8451, "pages": 82, "lang": "eng", "holdings": 9, "cover": "uc1.d0000652826"}, {"title": "Famous crimes and criminals /", "author": "Stevens, C. L. McCluer.", "id": "uga1.32108057371026", "lccA": "HV", "lccN": 6233, "pages": 284, "lang": "eng", "holdings": 5, "cover": "uga1.32108057371026"}, {"title": "A simple linebreeding program for poultry breeders /", "author": "Knox, Charles Webster, 1896-", "id": "uiug.30112019561940", "lccA": "HV", "lccN": 4981, "pages": 24, "lang": "eng", "holdings": 4, "cover": "uiug.30112019561940"}, {"title": "Inbreeding in relation to egg production /", "author": "Hays, F. A. 1888-", "id": "uiug.30112019621249", "lccA": "HV", "lccN": 4981, "pages": 56, "lang": "eng", "holdings": 5, "cover": "uiug.30112019621249"}, {"title": "Annual report - University Settlement Society of New York.", "author": "University Settlement Society of New York.", "id": "uiug.30112043506390", "lccA": "HV", "lccN": 4196, "pages": 532, "lang": "eng", "holdings": 8, "cover": "uiug.30112043506390"}, {"title": "Report of the proceedings of the ... Meeting of the Convention of American Instructors of the Deaf.", "author": "Convention of American Instructors of the Deaf. Meeting.", "id": "uiug.30112046365919", "lccA": "HV", "lccN": 2526, "pages": 196, "lang": "eng", "holdings": 67, "cover": "uiug.30112046365919"}, {"title": "The challenge of chronic diseases", "author": "Boas, Ernst Philip, 1891-", "id": "uiug.30112052126007", "lccA": "HV", "lccN": 3000, "pages": 228, "lang": "eng", "holdings": 48, "cover": "uiug.30112052126007"}, {"title": "Bolet\u00edn del Instituto Interamericano del Ni\u00f1o.", "author": "", "id": "uiug.30112052947550", "lccA": "HV", "lccN": 703, "pages": 610, "lang": "eng", "holdings": 67, "cover": "uiug.30112052947550"}, {"title": "The American issue.", "author": "", "id": "uiug.30112055359274", "lccA": "HV", "lccN": 5285, "pages": 314, "lang": "eng", "holdings": 29, "cover": "uiug.30112055359274"}, {"title": "Posters against alcoholism used in different countries /", "author": "World League Against Alcoholism.", "id": "uiug.30112058023109", "lccA": "HV", "lccN": 5072, "pages": 74, "lang": "eng", "holdings": 27, "cover": "uiug.30112058023109"}, {"title": "The administration of criminal justice in Illinois,", "author": "Bruce, Andrew A. 1866-1934.", "id": "uiug.30112061969694", "lccA": "HV", "lccN": 6793, "pages": 112, "lang": "eng", "holdings": 12, "cover": "uiug.30112061969694"}, {"title": "A study of problem boys and their brothers by the sub-commission on causes and effects of crime.", "author": "New York (State). Crime Commission", "id": "uiug.30112067002037", "lccA": "HV", "lccN": 9105, "pages": 416, "lang": "eng", "holdings": 65, "cover": "uiug.30112067002037"}, {"title": "The juvenile delinquent /", "author": "Shaw, Clifford R. 1895-1957.", "id": "uiug.30112069699814", "lccA": "HV", "lccN": 9105, "pages": 136, "lang": "eng", "holdings": 7, "cover": "uiug.30112069699814"}, {"title": "The social service exchange in Chicago,", "author": "Hughes, Elizabeth A. b. 1886.", "id": "uiug.30112072157230", "lccA": "HV", "lccN": 99, "pages": 140, "lang": "eng", "holdings": 83, "cover": "uiug.30112072157230"}, {"title": "Give prohibition its chance,", "author": "Boole, Ella A. 1858-1952.", "id": "uiug.30112078712772", "lccA": "HV", "lccN": 5089, "pages": 198, "lang": "eng", "holdings": 38, "cover": "uiug.30112078712772"}, {"title": "Biennial report of the Delaware Commission for the Blind.", "author": "Delaware. Commission for the Blind.", "id": "uiug.30112083798139", "lccA": "HV", "lccN": 1796, "pages": 280, "lang": "eng", "holdings": 3, "cover": "uiug.30112083798139"}, {"title": "Annual report.", "author": "New York (N.Y.). Dept. of Correction.", "id": "uiug.30112085196852", "lccA": "HV", "lccN": 8378, "pages": 188, "lang": "eng", "holdings": 26, "cover": "uiug.30112085196852"}, {"title": "Prohibition,", "author": "Kelsey, Rayner Wickersham, 1879-1934.", "id": "uiug.30112096617078", "lccA": "HV", "lccN": 5089, "pages": 40, "lang": "eng", "holdings": 12, "cover": "uiug.30112096617078"}, {"title": "Promotion of seamen's welfare in ports.", "author": "International Labour Office.", "id": "uiug.30112098204792", "lccA": "HV", "lccN": 3025, "pages": 178, "lang": "eng", "holdings": 23, "cover": "uiug.30112098204792"}, {"title": "Biennial report ..", "author": "Nebraska. State Penitentiary (Lincoln)", "id": "uiug.30112104311300", "lccA": "HV", "lccN": 8347, "pages": 30, "lang": "eng", "holdings": 3, "cover": "uiug.30112104311300"}, {"title": "Annual report of the Essex County Probation Department.", "author": "Essex County (N.J.). Probation Dept.", "id": "uiug.30112105324120", "lccA": "HV", "lccN": 9307, "pages": 188, "lang": "eng", "holdings": 14, "cover": "uiug.30112105324120"}, {"title": "Report,", "author": "Pennsylvania Association for the Blind.", "id": "uiug.30112105327180", "lccA": "HV", "lccN": 1788, "pages": 116, "lang": "eng", "holdings": 2, "cover": "uiug.30112105327180"}, {"title": "A guide for preparing annual police reports /", "author": "International Association of Chiefs of Police. Committee on Uniform Crime Records.", "id": "uiug.30112106750729", "lccA": "HV", "lccN": 7936, "pages": 40, "lang": "eng", "holdings": 40, "cover": "uiug.30112106750729"}, {"title": "Social work journal :", "author": "", "id": "uiug.30112106787507", "lccA": "HV", "lccN": 1, "pages": 124, "lang": "eng", "holdings": 122, "cover": "uiug.30112106787507"}, {"title": "In and about a grey stone manor house /", "author": "Matthews, William Henry, 1873-1946.", "id": "uiug.30112106900480", "lccA": "HV", "lccN": 1468, "pages": 100, "lang": "eng", "holdings": 10, "cover": "uiug.30112106900480"}, {"title": "Humane advocate.", "author": "", "id": "uiug.30112109810751", "lccA": "HV", "lccN": 4701, "pages": 524, "lang": "eng", "holdings": 7, "cover": "uiug.30112109810751"}, {"title": "Report of the ... annual meeting of the National Woman's Christian Temperance Union.", "author": "Woman's Christian Temperance Union.", "id": "uiug.30112109810850", "lccA": "HV", "lccN": 5228, "pages": 1740, "lang": "eng", "holdings": 3, "cover": "uiug.30112109810850"}, {"title": "[Report of the general director]", "author": "Jewish People's Institute of Chicago.", "id": "uiug.30112109842192", "lccA": "HV", "lccN": 4196, "pages": 190, "lang": "eng", "holdings": 13, "cover": "uiug.30112109842192"}, {"title": "Biennial report.", "author": "Missouri. Board of Managers of State Eleemosynary Institutions.", "id": "uiug.30112110866248", "lccA": "HV", "lccN": 86, "pages": 1146, "lang": "eng", "holdings": 14, "cover": "uiug.30112110866248"}, {"title": "Society and the child,", "author": "Clopper, Edward Nicholas, 1879-", "id": "uiug.30112111116163", "lccA": "HV", "lccN": 713, "pages": 216, "lang": "eng", "holdings": 32, "cover": "uiug.30112111116163"}, {"title": "Annual report.", "author": "Oklahoma. Department of Charities and Corrections.", "id": "uiug.30112117969557", "lccA": "HV", "lccN": 86, "pages": 1062, "lang": "eng", "holdings": 31, "cover": "uiug.30112117969557"}, {"title": "Problemy prestupnosti :", "author": "Gosudarstvennyi\u0306 institut po izuchenii\ufe20u\ufe21 prestupnosti i prestupnika (Soviet Union)", "id": "uiug.30112129191059", "lccA": "HV", "lccN": 7013, "pages": 308, "lang": "rus", "holdings": 3, "cover": "uiug.30112129191059"}, {"title": "Crime, degeneracy and immigration ;", "author": "Orebaugh, David A.", "id": "umn.31951001560791d", "lccA": "HV", "lccN": 6789, "pages": 298, "lang": "eng", "holdings": 46, "cover": "umn.31951001560791d"}, {"title": "Wild men of the wild West.", "author": "Sabin, Edwin L. 1870-1952.", "id": "umn.31951001560845g", "lccA": "HV", "lccN": 6446, "pages": 426, "lang": "eng", "holdings": 123, "cover": "umn.31951001560845g"}, {"title": "Public schools versus delinquent youth.", "author": "Vanden Bergh, Leonard John.", "id": "umn.31951001562168m", "lccA": "HV", "lccN": 9069, "pages": 260, "lang": "eng", "holdings": 27, "cover": "umn.31951001562168m"}, {"title": "The story of crime.", "author": "Harris, Louis (Judge)", "id": "umn.319510018733315", "lccA": "HV", "lccN": 6025, "pages": 360, "lang": "eng", "holdings": 32, "cover": "umn.319510018733315"}, {"title": "Nederstigen i do\u0308dsriket :", "author": "Lo-Johansson, Ivar, 1901-1990.", "id": "umn.31951002085982w", "lccA": "HV", "lccN": 4088, "pages": 236, "lang": "swe", "holdings": 7, "cover": "umn.31951002085982w"}, {"title": "La costituzione delinquenziale nella etiologia e terapia del delitto /", "author": "Di Tullio, Benigno.", "id": "umn.31951002117043v", "lccA": "HV", "lccN": 6038, "pages": 220, "lang": "ita", "holdings": 5, "cover": "umn.31951002117043v"}, {"title": "The history of the convict ship \"Success\" and dramatic story of some of the prisoners of the convict ship;", "author": "", "id": "umn.31951002173186t", "lccA": "HV", "lccN": 8949, "pages": 210, "lang": "eng", "holdings": 41, "cover": "umn.31951002173186t"}, {"title": "Report.", "author": "Florida. State Board of Public Welfare.", "id": "umn.31951002225523e", "lccA": "HV", "lccN": 86, "pages": 52, "lang": "eng", "holdings": 1, "cover": "umn.31951002225523e"}, {"title": "Annual report of the Ohio Department of Public Welfare.", "author": "Ohio. Department of Public Welfare.", "id": "umn.31951002240705l", "lccA": "HV", "lccN": 86, "pages": 132, "lang": "eng", "holdings": 3, "cover": "umn.31951002240705l"}, {"title": "The law of homicide and hurt in British India :", "author": "Rust, Philip John.", "id": "umn.319510023126488", "lccA": "HV", "lccN": 6499, "pages": 394, "lang": "eng", "holdings": 2, "cover": "umn.319510023126488"}, {"title": "The company of Cain.", "author": "Carthill, Al., d. 1935.", "id": "umn.31951002381982v", "lccA": "HV", "lccN": 7097, "pages": 338, "lang": "eng", "holdings": 28, "cover": "umn.31951002381982v"}, {"title": "What probation needs.", "author": "Paddon, Mary E.", "id": "umn.31951002647625s", "lccA": "HV", "lccN": 9305, "pages": 24, "lang": "eng", "holdings": 11, "cover": "umn.31951002647625s"}, {"title": "Juvenile delinquency :", "author": "Lenroot, Katharine F. 1891-1982.", "id": "umn.31951002669199x", "lccA": "HV", "lccN": 9104, "pages": 372, "lang": "eng", "holdings": 4, "cover": "umn.31951002669199x"}, {"title": "Revue internationale de l'enfant.", "author": "", "id": "umn.31951002795250i", "lccA": "HV", "lccN": 701, "pages": 460, "lang": "fre", "holdings": 23, "cover": "umn.31951002795250i"}, {"title": "Report.", "author": "New York (State). Department of Social Welfare.", "id": "umn.31951d00138801s", "lccA": "HV", "lccN": 86, "pages": 318, "lang": "eng", "holdings": 15, "cover": "umn.31951d00138801s"}, {"title": "Forschungen zur Alkoholfrage;", "author": "", "id": "umn.31951d00319399y", "lccA": "HV", "lccN": 5436, "pages": 388, "lang": "ger", "holdings": 1, "cover": "umn.31951d00319399y"}, {"title": "The end of prohibition.", "author": "Monroe, James Oliver, 1888-", "id": "umn.31951d007274233", "lccA": "HV", "lccN": 5089, "pages": 274, "lang": "eng", "holdings": 19, "cover": "umn.31951d007274233"}, {"title": "Administration report of the Inspector-General of Police.", "author": "Ceylon. Police Department.", "id": "umn.31951d013216328", "lccA": "HV", "lccN": 7809, "pages": 212, "lang": "eng", "holdings": 8, "cover": "umn.31951d013216328"}, {"title": "Annual report of the State Public Welfare Commission to the General Assembly at its January session.", "author": "Rhode Island. State Public Welfare Commission.", "id": "umn.31951d03021036t", "lccA": "HV", "lccN": 98, "pages": 22, "lang": "eng", "holdings": 4, "cover": "umn.31951d03021036t"}, {"title": "Child welfare extension service. :", "author": "United States. Congress. House. Committee on Interstate and Foreign Commerce.", "id": "umn.31951d03518346m", "lccA": "HV", "lccN": 741, "pages": 300, "lang": "eng", "holdings": 23, "cover": "umn.31951d03518346m"}, {"title": "Cost of prohibition and your income tax /", "author": "", "id": "umn.31951p00070062f", "lccA": "HV", "lccN": 5089, "pages": 22, "lang": "eng", "holdings": 31, "cover": "umn.31951p00070062f"}, {"title": "Government liquor control in Canada /", "author": "", "id": "umn.31951p00296879i", "lccA": "HV", "lccN": 5015, "pages": 62, "lang": "eng", "holdings": 1, "cover": "umn.31951p00296879i"}, {"title": "Det svenska samha\u0308llet och arbetslo\u0308sheten 1914-1924 :", "author": "Sweden. Statens arbetslo\u0308shetskommission.", "id": "umn.31951t00089058n", "lccA": "HV", "lccN": 336, "pages": 698, "lang": "swe", "holdings": 8, "cover": "umn.31951t00089058n"}, {"title": "A handbook of social work ...", "author": "Minnesota State Conference and Institute of Social Work.", "id": "umn.31951t00089101c", "lccA": "HV", "lccN": 40, "pages": 196, "lang": "eng", "holdings": 4, "cover": "umn.31951t00089101c"}, {"title": "Report of the Commissioner of Charities and Corrections.", "author": "Oklahoma. Department of Charities and Corrections.", "id": "umn.31951t00089208u", "lccA": "HV", "lccN": 86, "pages": 378, "lang": "eng", "holdings": 7, "cover": "umn.31951t00089208u"}, {"title": "The mystery of Jack the Ripper /", "author": "Matters, Leonard.", "id": "uva.x000089231", "lccA": "HV", "lccN": 6535, "pages": 162, "lang": "eng", "holdings": 20, "cover": "uva.x000089231"}, {"title": "To the pure ...", "author": "Ernst, Morris L. 1888-1976", "id": "uva.x000391427", "lccA": "HV", "lccN": 6727, "pages": 364, "lang": "eng", "holdings": 15, "cover": "uva.x000391427"}, {"title": "Neighbors all,", "author": "Barrows, Esther G.", "id": "uva.x001469626", "lccA": "HV", "lccN": 4196, "pages": 240, "lang": "eng", "holdings": 75, "cover": "uva.x001469626"}, {"title": "The Bureau of porhibition, its history,", "author": "Schmeckebier, Laurence F. 1877-1959", "id": "uva.x004576029", "lccA": "HV", "lccN": 5089, "pages": 360, "lang": "eng", "holdings": 157, "cover": "uva.x004576029"}, {"title": "Police problems in the light of modern science /", "author": "Barry, Alfred Glen.", "id": "wu.89006103089", "lccA": "HV", "lccN": 8143, "pages": 528, "lang": "eng", "holdings": 1, "cover": "wu.89006103089"}, {"title": "The penology of Jeremy Bentham /", "author": "Person, Philip Hilmar.", "id": "wu.89060160603", "lccA": "HV", "lccN": 8675, "pages": 582, "lang": "eng", "holdings": 1, "cover": "wu.89060160603"}, {"title": "Directory of family social work societies of the United States and Canada :", "author": "", "id": "wu.89091456640", "lccA": "HV", "lccN": 89, "pages": 40, "lang": "eng", "holdings": 1, "cover": "wu.89091456640"}, {"title": "Cro\u0301nica del crimen /", "author": "Jime\u0301nez de Asu\u0301a, Luis, 1889-1970.", "id": "wu.89092543602", "lccA": "HV", "lccN": 6028, "pages": 288, "lang": "spa", "holdings": 11, "cover": "wu.89092543602"}, {"title": "How the feebleminded live in the community :", "author": "Town, Clara Harrison.", "id": "wu.89095169652", "lccA": "HV", "lccN": 3006, "pages": 296, "lang": "eng", "holdings": 26, "cover": "wu.89095169652"}, {"title": "Vocational aspects of psychiatric social work :", "author": "American Association of Social Workers.", "id": "wu.89095281028", "lccA": "HV", "lccN": 689, "pages": 54, "lang": "eng", "holdings": 7, "cover": "wu.89095281028"}, {"title": "Scotland Yard :", "author": "Dilnot, George, 1883-1951.", "id": "wu.89095808069", "lccA": "HV", "lccN": 8198, "pages": 400, "lang": "eng", "holdings": 20, "cover": "wu.89095808069"}, {"title": "De burgerrechtelijke gezinsvoogdij ... /", "author": "Zuyderhoff, Jean Constant Louis.", "id": "wu.89098711930", "lccA": "HV", "lccN": 776, "pages": 242, "lang": "dut", "holdings": 6, "cover": "wu.89098711930"}, {"title": "Laws of Pennsylvania relating to social work,", "author": "Bradway, John S. 1890-1985.", "id": "wu.89098714207", "lccA": "HV", "lccN": 75, "pages": 296, "lang": "eng", "holdings": 34, "cover": "wu.89098714207"}, {"title": "Report.", "author": "Buhl Foundation.", "id": "wu.89100378033", "lccA": "HV", "lccN": 99, "pages": 46, "lang": "eng", "holdings": 21, "cover": "wu.89100378033"}]